<?xml version="1.0" encoding="UTF-8"?>
<root t='150' id='1' V150='13' creationTimestamp='0x17689ead4b4' V1='4' name='MATMAS01Res' incarnation='233'>
  <rootElem t='167' id='2' V167='21' V283='2' occurMinTimes='1' occurMaxTimes='1' minSize='-1' maxSize='-1' groupType='1' repHandlerStruct='' visible='true' inheritsFrom='' V281='13' V1='4' name='MATMAS01'>
    <structNode t='150' idref='1'/>
    <child t='167' id='3' V167='21' V283='2' occurMinTimes='1' occurMaxTimes='1' minSize='-1' maxSize='-1' groupType='1' repHandlerStruct='' visible='true' inheritsFrom='' V281='13' V1='4' name='IDOC'>
      <structNode t='150' idref='1'/>
      <child t='167' id='4' V167='21' V283='2' occurMaxTimes='1' minSize='-1' maxSize='-1' groupType='3' repHandlerStruct='' inheritsFrom='' V281='13' V1='4' name='Attributes'>
        <structNode t='150' idref='1'/>
        <child t='167' id='5' V167='21' V283='2' occurMinTimes='1' occurMaxTimes='1' minSize='-1' maxSize='-1' dataType='2' elemType='1' repHandlerStruct='' visible='true' inheritsFrom='' V281='13' V1='4' name='BEGIN'>
          <structNode t='150' idref='1'/>
        </child>
      </child>
      <child t='167' id='6' V167='21' V283='2' occurMinTimes='1' occurMaxTimes='1' minSize='-1' maxSize='-1' groupType='1' repHandlerStruct='' visible='true' inheritsFrom='' V281='13' V1='4' name='EDI_DC40' checksumValid='true' checksum='wovSzwtmKTdYn6xd1FKKNoKT9ZA='>
        <structNode t='150' idref='1'/>
        <child t='167' id='7' V167='21' V283='2' occurMaxTimes='1' minSize='-1' maxSize='-1' groupType='3' repHandlerStruct='' inheritsFrom='' V281='13' V1='4' name='Attributes'>
          <structNode t='150' idref='1'/>
          <child t='167' id='8' V167='21' V283='2' occurMinTimes='1' occurMaxTimes='1' minSize='-1' maxSize='-1' dataType='2' elemType='1' repHandlerStruct='' visible='true' inheritsFrom='' V281='13' V1='4' name='SEGMENT'>
            <structNode t='150' idref='1'/>
          </child>
        </child>
        <child t='167' id='9' V167='21' V283='2' occurMinTimes='1' occurMaxTimes='1' minSize='-1' maxSize='-1' dataType='2' repHandlerStruct='' visible='true' inheritsFrom='' V281='13' V1='4' name='TABNAM'>
          <structNode t='150' idref='1'/>
        </child>
        <child t='167' id='10' V167='21' V283='2' occurMinTimes='1' occurMaxTimes='1' minSize='-1' maxSize='-1' dataType='2' repHandlerStruct='' visible='true' inheritsFrom='' V281='13' V1='4' name='MANDT'>
          <structNode t='150' idref='1'/>
        </child>
        <child t='167' id='11' V167='21' V283='2' occurMinTimes='1' occurMaxTimes='1' minSize='-1' maxSize='-1' dataType='2' repHandlerStruct='' visible='true' inheritsFrom='' V281='13' V1='4' name='DOCNUM'>
          <structNode t='150' idref='1'/>
        </child>
        <child t='167' id='12' V167='21' V283='2' occurMinTimes='1' occurMaxTimes='1' minSize='-1' maxSize='-1' dataType='2' repHandlerStruct='' visible='true' inheritsFrom='' V281='13' V1='4' name='DOCREL'>
          <structNode t='150' idref='1'/>
        </child>
        <child t='167' id='13' V167='21' V283='2' occurMinTimes='1' occurMaxTimes='1' minSize='-1' maxSize='-1' dataType='2' repHandlerStruct='' visible='true' inheritsFrom='' V281='13' V1='4' name='STATUS'>
          <structNode t='150' idref='1'/>
        </child>
        <child t='167' id='14' V167='21' V283='2' occurMinTimes='1' occurMaxTimes='1' minSize='-1' maxSize='-1' dataType='2' repHandlerStruct='' visible='true' inheritsFrom='' V281='13' V1='4' name='DIRECT'>
          <structNode t='150' idref='1'/>
        </child>
        <child t='167' id='15' V167='21' V283='2' occurMinTimes='1' occurMaxTimes='1' minSize='-1' maxSize='-1' dataType='2' repHandlerStruct='' visible='true' inheritsFrom='' V281='13' V1='4' name='OUTMOD'>
          <structNode t='150' idref='1'/>
        </child>
        <child t='167' id='16' V167='21' V283='2' occurMinTimes='1' occurMaxTimes='1' minSize='-1' maxSize='-1' dataType='2' repHandlerStruct='' visible='true' inheritsFrom='' V281='13' V1='4' name='IDOCTYP'>
          <structNode t='150' idref='1'/>
        </child>
        <child t='167' id='17' V167='21' V283='2' occurMinTimes='1' occurMaxTimes='1' minSize='-1' maxSize='-1' dataType='2' repHandlerStruct='' visible='true' inheritsFrom='' V281='13' V1='4' name='MESTYP'>
          <structNode t='150' idref='1'/>
        </child>
        <child t='167' id='18' V167='21' V283='2' occurMinTimes='1' occurMaxTimes='1' minSize='-1' maxSize='-1' dataType='2' repHandlerStruct='' visible='true' inheritsFrom='' V281='13' V1='4' name='SNDPOR'>
          <structNode t='150' idref='1'/>
        </child>
        <child t='167' id='19' V167='21' V283='2' occurMinTimes='1' occurMaxTimes='1' minSize='-1' maxSize='-1' dataType='2' repHandlerStruct='' visible='true' inheritsFrom='' V281='13' V1='4' name='SNDPRT'>
          <structNode t='150' idref='1'/>
        </child>
        <child t='167' id='20' V167='21' V283='2' occurMinTimes='1' occurMaxTimes='1' minSize='-1' maxSize='-1' dataType='2' repHandlerStruct='' visible='true' inheritsFrom='' V281='13' V1='4' name='SNDPRN'>
          <structNode t='150' idref='1'/>
        </child>
        <child t='167' id='21' V167='21' V283='2' occurMinTimes='1' occurMaxTimes='1' minSize='-1' maxSize='-1' dataType='2' repHandlerStruct='' visible='true' inheritsFrom='' V281='13' V1='4' name='RCVPOR'>
          <structNode t='150' idref='1'/>
        </child>
        <child t='167' id='22' V167='21' V283='2' occurMinTimes='1' occurMaxTimes='1' minSize='-1' maxSize='-1' dataType='2' repHandlerStruct='' visible='true' inheritsFrom='' V281='13' V1='4' name='RCVPRT'>
          <structNode t='150' idref='1'/>
        </child>
        <child t='167' id='23' V167='21' V283='2' occurMinTimes='1' occurMaxTimes='1' minSize='-1' maxSize='-1' dataType='2' repHandlerStruct='' visible='true' inheritsFrom='' V281='13' V1='4' name='RCVPRN'>
          <structNode t='150' idref='1'/>
        </child>
        <child t='167' id='24' V167='21' V283='2' occurMinTimes='1' occurMaxTimes='1' minSize='-1' maxSize='-1' dataType='2' repHandlerStruct='' visible='true' inheritsFrom='' V281='13' V1='4' name='CREDAT'>
          <structNode t='150' idref='1'/>
        </child>
        <child t='167' id='25' V167='21' V283='2' occurMinTimes='1' occurMaxTimes='1' minSize='-1' maxSize='-1' dataType='2' repHandlerStruct='' visible='true' inheritsFrom='' V281='13' V1='4' name='CRETIM'>
          <structNode t='150' idref='1'/>
        </child>
        <child t='167' id='26' V167='21' V283='2' occurMinTimes='1' occurMaxTimes='1' minSize='-1' maxSize='-1' dataType='2' repHandlerStruct='' visible='true' inheritsFrom='' V281='13' V1='4' name='SERIAL'>
          <structNode t='150' idref='1'/>
        </child>
      </child>
      <child t='167' id='27' V167='21' V283='2' occurMinTimes='1' occurMaxTimes='1' minSize='-1' maxSize='-1' groupType='1' repHandlerStruct='' visible='true' inheritsFrom='' V281='13' V1='4' name='E1MARAM' checksumValid='true' checksum='hkTTmAH00ckgYkH/8lezWXfP57A='>
        <structNode t='150' idref='1'/>
        <child t='167' id='28' V167='21' V283='2' occurMaxTimes='1' minSize='-1' maxSize='-1' groupType='3' repHandlerStruct='' inheritsFrom='' V281='13' V1='4' name='Attributes'>
          <structNode t='150' idref='1'/>
          <child t='167' id='29' V167='21' V283='2' occurMinTimes='1' occurMaxTimes='1' minSize='-1' maxSize='-1' dataType='2' elemType='1' repHandlerStruct='' visible='true' inheritsFrom='' V281='13' V1='4' name='SEGMENT'>
            <structNode t='150' idref='1'/>
          </child>
        </child>
        <child t='167' id='30' V167='21' V283='2' occurMinTimes='1' occurMaxTimes='1' minSize='-1' maxSize='-1' dataType='2' repHandlerStruct='' visible='true' inheritsFrom='' V281='13' V1='4' name='MSGFN'>
          <structNode t='150' idref='1'/>
        </child>
        <child t='167' id='31' V167='21' V283='2' occurMinTimes='1' occurMaxTimes='1' minSize='-1' maxSize='-1' dataType='2' repHandlerStruct='' visible='true' inheritsFrom='' V281='13' V1='4' name='MATNR'>
          <structNode t='150' idref='1'/>
        </child>
        <child t='167' id='32' V167='21' V283='2' occurMinTimes='1' occurMaxTimes='1' minSize='-1' maxSize='-1' dataType='2' repHandlerStruct='' visible='true' inheritsFrom='' V281='13' V1='4' name='ERSDA'>
          <structNode t='150' idref='1'/>
        </child>
        <child t='167' id='33' V167='21' V283='2' occurMinTimes='1' occurMaxTimes='1' minSize='-1' maxSize='-1' dataType='2' repHandlerStruct='' visible='true' inheritsFrom='' V281='13' V1='4' name='ERNAM'>
          <structNode t='150' idref='1'/>
        </child>
        <child t='167' id='34' V167='21' V283='2' occurMinTimes='1' occurMaxTimes='1' minSize='-1' maxSize='-1' dataType='2' repHandlerStruct='' visible='true' inheritsFrom='' V281='13' V1='4' name='LAEDA'>
          <structNode t='150' idref='1'/>
        </child>
        <child t='167' id='35' V167='21' V283='2' occurMinTimes='1' occurMaxTimes='1' minSize='-1' maxSize='-1' dataType='2' repHandlerStruct='' visible='true' inheritsFrom='' V281='13' V1='4' name='AENAM'>
          <structNode t='150' idref='1'/>
        </child>
        <child t='167' id='36' V167='21' V283='2' occurMinTimes='1' occurMaxTimes='1' minSize='-1' maxSize='-1' dataType='2' repHandlerStruct='' visible='true' inheritsFrom='' V281='13' V1='4' name='PSTAT'>
          <structNode t='150' idref='1'/>
        </child>
        <child t='167' id='37' V167='21' V283='2' occurMinTimes='1' occurMaxTimes='1' minSize='-1' maxSize='-1' dataType='2' repHandlerStruct='' visible='true' inheritsFrom='' V281='13' V1='4' name='MTART'>
          <structNode t='150' idref='1'/>
        </child>
        <child t='167' id='38' V167='21' V283='2' occurMinTimes='1' occurMaxTimes='1' minSize='-1' maxSize='-1' dataType='2' repHandlerStruct='' visible='true' inheritsFrom='' V281='13' V1='4' name='MBRSH'>
          <structNode t='150' idref='1'/>
        </child>
        <child t='167' id='39' V167='21' V283='2' occurMinTimes='1' occurMaxTimes='1' minSize='-1' maxSize='-1' dataType='2' repHandlerStruct='' visible='true' inheritsFrom='' V281='13' V1='4' name='MATKL'>
          <structNode t='150' idref='1'/>
        </child>
        <child t='167' id='40' V167='21' V283='2' occurMinTimes='1' occurMaxTimes='1' minSize='-1' maxSize='-1' dataType='2' repHandlerStruct='' visible='true' inheritsFrom='' V281='13' V1='4' name='MEINS'>
          <structNode t='150' idref='1'/>
        </child>
        <child t='167' id='41' V167='21' V283='2' occurMinTimes='1' occurMaxTimes='1' minSize='-1' maxSize='-1' dataType='2' repHandlerStruct='' visible='true' inheritsFrom='' V281='13' V1='4' name='BLANZ'>
          <structNode t='150' idref='1'/>
        </child>
        <child t='167' id='42' V167='21' V283='2' occurMinTimes='1' occurMaxTimes='1' minSize='-1' maxSize='-1' dataType='2' repHandlerStruct='' visible='true' inheritsFrom='' V281='13' V1='4' name='BRGEW'>
          <structNode t='150' idref='1'/>
        </child>
        <child t='167' id='43' V167='21' V283='2' occurMinTimes='1' occurMaxTimes='1' minSize='-1' maxSize='-1' dataType='2' repHandlerStruct='' visible='true' inheritsFrom='' V281='13' V1='4' name='NTGEW'>
          <structNode t='150' idref='1'/>
        </child>
        <child t='167' id='44' V167='21' V283='2' occurMinTimes='1' occurMaxTimes='1' minSize='-1' maxSize='-1' dataType='2' repHandlerStruct='' visible='true' inheritsFrom='' V281='13' V1='4' name='GEWEI'>
          <structNode t='150' idref='1'/>
        </child>
        <child t='167' id='45' V167='21' V283='2' occurMinTimes='1' occurMaxTimes='1' minSize='-1' maxSize='-1' dataType='2' repHandlerStruct='' visible='true' inheritsFrom='' V281='13' V1='4' name='VOLUM'>
          <structNode t='150' idref='1'/>
        </child>
        <child t='167' id='46' V167='21' V283='2' occurMinTimes='1' occurMaxTimes='1' minSize='-1' maxSize='-1' dataType='2' repHandlerStruct='' visible='true' inheritsFrom='' V281='13' V1='4' name='TRAGR'>
          <structNode t='150' idref='1'/>
        </child>
        <child t='167' id='47' V167='21' V283='2' occurMinTimes='1' occurMaxTimes='1' minSize='-1' maxSize='-1' dataType='2' repHandlerStruct='' visible='true' inheritsFrom='' V281='13' V1='4' name='SPART'>
          <structNode t='150' idref='1'/>
        </child>
        <child t='167' id='48' V167='21' V283='2' occurMinTimes='1' occurMaxTimes='1' minSize='-1' maxSize='-1' dataType='2' repHandlerStruct='' visible='true' inheritsFrom='' V281='13' V1='4' name='WESCH'>
          <structNode t='150' idref='1'/>
        </child>
        <child t='167' id='49' V167='21' V283='2' occurMinTimes='1' occurMaxTimes='1' minSize='-1' maxSize='-1' dataType='2' repHandlerStruct='' visible='true' inheritsFrom='' V281='13' V1='4' name='LAENG'>
          <structNode t='150' idref='1'/>
        </child>
        <child t='167' id='50' V167='21' V283='2' occurMinTimes='1' occurMaxTimes='1' minSize='-1' maxSize='-1' dataType='2' repHandlerStruct='' visible='true' inheritsFrom='' V281='13' V1='4' name='BREIT'>
          <structNode t='150' idref='1'/>
        </child>
        <child t='167' id='51' V167='21' V283='2' occurMinTimes='1' occurMaxTimes='1' minSize='-1' maxSize='-1' dataType='2' repHandlerStruct='' visible='true' inheritsFrom='' V281='13' V1='4' name='HOEHE'>
          <structNode t='150' idref='1'/>
        </child>
        <child t='167' id='52' V167='21' V283='2' occurMinTimes='1' occurMaxTimes='1' minSize='-1' maxSize='-1' dataType='2' repHandlerStruct='' visible='true' inheritsFrom='' V281='13' V1='4' name='ERGEW'>
          <structNode t='150' idref='1'/>
        </child>
        <child t='167' id='53' V167='21' V283='2' occurMinTimes='1' occurMaxTimes='1' minSize='-1' maxSize='-1' dataType='2' repHandlerStruct='' visible='true' inheritsFrom='' V281='13' V1='4' name='ERVOL'>
          <structNode t='150' idref='1'/>
        </child>
        <child t='167' id='54' V167='21' V283='2' occurMinTimes='1' occurMaxTimes='1' minSize='-1' maxSize='-1' dataType='2' repHandlerStruct='' visible='true' inheritsFrom='' V281='13' V1='4' name='GEWTO'>
          <structNode t='150' idref='1'/>
        </child>
        <child t='167' id='55' V167='21' V283='2' occurMinTimes='1' occurMaxTimes='1' minSize='-1' maxSize='-1' dataType='2' repHandlerStruct='' visible='true' inheritsFrom='' V281='13' V1='4' name='VOLTO'>
          <structNode t='150' idref='1'/>
        </child>
        <child t='167' id='56' V167='21' V283='2' occurMinTimes='1' occurMaxTimes='1' minSize='-1' maxSize='-1' dataType='2' repHandlerStruct='' visible='true' inheritsFrom='' V281='13' V1='4' name='FUELG'>
          <structNode t='150' idref='1'/>
        </child>
        <child t='167' id='57' V167='21' V283='2' occurMinTimes='1' occurMaxTimes='1' minSize='-1' maxSize='-1' dataType='2' repHandlerStruct='' visible='true' inheritsFrom='' V281='13' V1='4' name='STFAK'>
          <structNode t='150' idref='1'/>
        </child>
        <child t='167' id='58' V167='21' V283='2' occurMinTimes='1' occurMaxTimes='1' minSize='-1' maxSize='-1' dataType='2' repHandlerStruct='' visible='true' inheritsFrom='' V281='13' V1='4' name='MHDRZ'>
          <structNode t='150' idref='1'/>
        </child>
        <child t='167' id='59' V167='21' V283='2' occurMinTimes='1' occurMaxTimes='1' minSize='-1' maxSize='-1' dataType='2' repHandlerStruct='' visible='true' inheritsFrom='' V281='13' V1='4' name='MHDHB'>
          <structNode t='150' idref='1'/>
        </child>
        <child t='167' id='60' V167='21' V283='2' occurMinTimes='1' occurMaxTimes='1' minSize='-1' maxSize='-1' dataType='2' repHandlerStruct='' visible='true' inheritsFrom='' V281='13' V1='4' name='MHDLP'>
          <structNode t='150' idref='1'/>
        </child>
        <child t='167' id='61' V167='21' V283='2' occurMinTimes='1' occurMaxTimes='1' minSize='-1' maxSize='-1' dataType='2' repHandlerStruct='' visible='true' inheritsFrom='' V281='13' V1='4' name='VPSTA'>
          <structNode t='150' idref='1'/>
        </child>
        <child t='167' id='62' V167='21' V283='2' occurMinTimes='1' occurMaxTimes='1' minSize='-1' maxSize='-1' dataType='2' repHandlerStruct='' visible='true' inheritsFrom='' V281='13' V1='4' name='MSTDE'>
          <structNode t='150' idref='1'/>
        </child>
        <child t='167' id='63' V167='21' V283='2' occurMinTimes='1' occurMaxTimes='1' minSize='-1' maxSize='-1' dataType='2' repHandlerStruct='' visible='true' inheritsFrom='' V281='13' V1='4' name='MSTDV'>
          <structNode t='150' idref='1'/>
        </child>
        <child t='167' id='64' V167='21' V283='2' occurMinTimes='1' occurMaxTimes='1' minSize='-1' maxSize='-1' dataType='2' repHandlerStruct='' visible='true' inheritsFrom='' V281='13' V1='4' name='COMPL'>
          <structNode t='150' idref='1'/>
        </child>
        <child t='167' id='65' V167='21' V283='2' occurMinTimes='1' occurMaxTimes='1' minSize='-1' maxSize='-1' dataType='2' repHandlerStruct='' visible='true' inheritsFrom='' V281='13' V1='4' name='MTPOS_MARA'>
          <structNode t='150' idref='1'/>
        </child>
        <child t='167' id='66' V167='21' V283='2' occurMinTimes='1' occurMaxTimes='1' minSize='-1' maxSize='-1' dataType='2' repHandlerStruct='' visible='true' inheritsFrom='' V281='13' V1='4' name='GEWTO_NEW'>
          <structNode t='150' idref='1'/>
        </child>
        <child t='167' id='67' V167='21' V283='2' occurMinTimes='1' occurMaxTimes='1' minSize='-1' maxSize='-1' dataType='2' repHandlerStruct='' visible='true' inheritsFrom='' V281='13' V1='4' name='VOLTO_NEW'>
          <structNode t='150' idref='1'/>
        </child>
        <child t='167' id='68' V167='21' V283='2' occurMinTimes='1' occurMaxTimes='1' minSize='-1' maxSize='-1' dataType='2' repHandlerStruct='' visible='true' inheritsFrom='' V281='13' V1='4' name='ANP'>
          <structNode t='150' idref='1'/>
        </child>
        <child t='167' id='69' V167='21' V283='2' occurMinTimes='1' occurMaxTimes='1' minSize='-1' maxSize='-1' dataType='2' repHandlerStruct='' visible='true' inheritsFrom='' V281='13' V1='4' name='MATNR_LONG'>
          <structNode t='150' idref='1'/>
        </child>
        <child t='167' id='70' V167='21' V283='2' occurMinTimes='1' occurMaxTimes='1' minSize='-1' maxSize='-1' groupType='1' repHandlerStruct='' visible='true' inheritsFrom='' V281='13' V1='4' name='E1MAKTM'>
          <structNode t='150' idref='1'/>
          <child t='167' id='71' V167='21' V283='2' occurMaxTimes='1' minSize='-1' maxSize='-1' groupType='3' repHandlerStruct='' inheritsFrom='' V281='13' V1='4' name='Attributes'>
            <structNode t='150' idref='1'/>
            <child t='167' id='72' V167='21' V283='2' occurMinTimes='1' occurMaxTimes='1' minSize='-1' maxSize='-1' dataType='2' elemType='1' repHandlerStruct='' visible='true' inheritsFrom='' V281='13' V1='4' name='SEGMENT'>
              <structNode t='150' idref='1'/>
            </child>
          </child>
          <child t='167' id='73' V167='21' V283='2' occurMinTimes='1' occurMaxTimes='1' minSize='-1' maxSize='-1' dataType='2' repHandlerStruct='' visible='true' inheritsFrom='' V281='13' V1='4' name='MSGFN'>
            <structNode t='150' idref='1'/>
          </child>
          <child t='167' id='74' V167='21' V283='2' occurMinTimes='1' occurMaxTimes='1' minSize='-1' maxSize='-1' dataType='2' repHandlerStruct='' visible='true' inheritsFrom='' V281='13' V1='4' name='SPRAS'>
            <structNode t='150' idref='1'/>
          </child>
          <child t='167' id='75' V167='21' V283='2' occurMinTimes='1' occurMaxTimes='1' minSize='-1' maxSize='-1' dataType='2' repHandlerStruct='' visible='true' inheritsFrom='' V281='13' V1='4' name='MAKTX'>
            <structNode t='150' idref='1'/>
          </child>
          <child t='167' id='76' V167='21' V283='2' occurMinTimes='1' occurMaxTimes='1' minSize='-1' maxSize='-1' dataType='2' repHandlerStruct='' visible='true' inheritsFrom='' V281='13' V1='4' name='SPRAS_ISO'>
            <structNode t='150' idref='1'/>
          </child>
        </child>
        <child t='167' id='77' V167='21' V283='2' occurMinTimes='1' occurMaxTimes='1' minSize='-1' maxSize='-1' groupType='1' repHandlerStruct='' visible='true' inheritsFrom='' V281='13' V1='4' name='E1MARCM' checksumValid='true' checksum='sTRtB7xKTVrUEO8bJ9qNB4bwf1o='>
          <structNode t='150' idref='1'/>
          <child t='167' id='78' V167='21' V283='2' occurMaxTimes='1' minSize='-1' maxSize='-1' groupType='3' repHandlerStruct='' inheritsFrom='' V281='13' V1='4' name='Attributes'>
            <structNode t='150' idref='1'/>
            <child t='167' id='79' V167='21' V283='2' occurMinTimes='1' occurMaxTimes='1' minSize='-1' maxSize='-1' dataType='2' elemType='1' repHandlerStruct='' visible='true' inheritsFrom='' V281='13' V1='4' name='SEGMENT'>
              <structNode t='150' idref='1'/>
            </child>
          </child>
          <child t='167' id='80' V167='21' V283='2' occurMinTimes='1' occurMaxTimes='1' minSize='-1' maxSize='-1' dataType='2' repHandlerStruct='' visible='true' inheritsFrom='' V281='13' V1='4' name='MSGFN'>
            <structNode t='150' idref='1'/>
          </child>
          <child t='167' id='81' V167='21' V283='2' occurMinTimes='1' occurMaxTimes='1' minSize='-1' maxSize='-1' dataType='2' repHandlerStruct='' visible='true' inheritsFrom='' V281='13' V1='4' name='WERKS'>
            <structNode t='150' idref='1'/>
          </child>
          <child t='167' id='82' V167='21' V283='2' occurMinTimes='1' occurMaxTimes='1' minSize='-1' maxSize='-1' dataType='2' repHandlerStruct='' visible='true' inheritsFrom='' V281='13' V1='4' name='PSTAT'>
            <structNode t='150' idref='1'/>
          </child>
          <child t='167' id='83' V167='21' V283='2' occurMinTimes='1' occurMaxTimes='1' minSize='-1' maxSize='-1' dataType='2' repHandlerStruct='' visible='true' inheritsFrom='' V281='13' V1='4' name='PLIFZ'>
            <structNode t='150' idref='1'/>
          </child>
          <child t='167' id='84' V167='21' V283='2' occurMinTimes='1' occurMaxTimes='1' minSize='-1' maxSize='-1' dataType='2' repHandlerStruct='' visible='true' inheritsFrom='' V281='13' V1='4' name='WEBAZ'>
            <structNode t='150' idref='1'/>
          </child>
          <child t='167' id='85' V167='21' V283='2' occurMinTimes='1' occurMaxTimes='1' minSize='-1' maxSize='-1' dataType='2' repHandlerStruct='' visible='true' inheritsFrom='' V281='13' V1='4' name='PERKZ'>
            <structNode t='150' idref='1'/>
          </child>
          <child t='167' id='86' V167='21' V283='2' occurMinTimes='1' occurMaxTimes='1' minSize='-1' maxSize='-1' dataType='2' repHandlerStruct='' visible='true' inheritsFrom='' V281='13' V1='4' name='AUSSS'>
            <structNode t='150' idref='1'/>
          </child>
          <child t='167' id='87' V167='21' V283='2' occurMinTimes='1' occurMaxTimes='1' minSize='-1' maxSize='-1' dataType='2' repHandlerStruct='' visible='true' inheritsFrom='' V281='13' V1='4' name='MINBE'>
            <structNode t='150' idref='1'/>
          </child>
          <child t='167' id='88' V167='21' V283='2' occurMinTimes='1' occurMaxTimes='1' minSize='-1' maxSize='-1' dataType='2' repHandlerStruct='' visible='true' inheritsFrom='' V281='13' V1='4' name='EISBE'>
            <structNode t='150' idref='1'/>
          </child>
          <child t='167' id='89' V167='21' V283='2' occurMinTimes='1' occurMaxTimes='1' minSize='-1' maxSize='-1' dataType='2' repHandlerStruct='' visible='true' inheritsFrom='' V281='13' V1='4' name='BSTMI'>
            <structNode t='150' idref='1'/>
          </child>
          <child t='167' id='90' V167='21' V283='2' occurMinTimes='1' occurMaxTimes='1' minSize='-1' maxSize='-1' dataType='2' repHandlerStruct='' visible='true' inheritsFrom='' V281='13' V1='4' name='BSTMA'>
            <structNode t='150' idref='1'/>
          </child>
          <child t='167' id='91' V167='21' V283='2' occurMinTimes='1' occurMaxTimes='1' minSize='-1' maxSize='-1' dataType='2' repHandlerStruct='' visible='true' inheritsFrom='' V281='13' V1='4' name='BSTFE'>
            <structNode t='150' idref='1'/>
          </child>
          <child t='167' id='92' V167='21' V283='2' occurMinTimes='1' occurMaxTimes='1' minSize='-1' maxSize='-1' dataType='2' repHandlerStruct='' visible='true' inheritsFrom='' V281='13' V1='4' name='BSTRF'>
            <structNode t='150' idref='1'/>
          </child>
          <child t='167' id='93' V167='21' V283='2' occurMinTimes='1' occurMaxTimes='1' minSize='-1' maxSize='-1' dataType='2' repHandlerStruct='' visible='true' inheritsFrom='' V281='13' V1='4' name='MABST'>
            <structNode t='150' idref='1'/>
          </child>
          <child t='167' id='94' V167='21' V283='2' occurMinTimes='1' occurMaxTimes='1' minSize='-1' maxSize='-1' dataType='2' repHandlerStruct='' visible='true' inheritsFrom='' V281='13' V1='4' name='LOSFX'>
            <structNode t='150' idref='1'/>
          </child>
          <child t='167' id='95' V167='21' V283='2' occurMinTimes='1' occurMaxTimes='1' minSize='-1' maxSize='-1' dataType='2' repHandlerStruct='' visible='true' inheritsFrom='' V281='13' V1='4' name='AUSDT'>
            <structNode t='150' idref='1'/>
          </child>
          <child t='167' id='96' V167='21' V283='2' occurMinTimes='1' occurMaxTimes='1' minSize='-1' maxSize='-1' dataType='2' repHandlerStruct='' visible='true' inheritsFrom='' V281='13' V1='4' name='BEARZ'>
            <structNode t='150' idref='1'/>
          </child>
          <child t='167' id='97' V167='21' V283='2' occurMinTimes='1' occurMaxTimes='1' minSize='-1' maxSize='-1' dataType='2' repHandlerStruct='' visible='true' inheritsFrom='' V281='13' V1='4' name='RUEZT'>
            <structNode t='150' idref='1'/>
          </child>
          <child t='167' id='98' V167='21' V283='2' occurMinTimes='1' occurMaxTimes='1' minSize='-1' maxSize='-1' dataType='2' repHandlerStruct='' visible='true' inheritsFrom='' V281='13' V1='4' name='TRANZ'>
            <structNode t='150' idref='1'/>
          </child>
          <child t='167' id='99' V167='21' V283='2' occurMinTimes='1' occurMaxTimes='1' minSize='-1' maxSize='-1' dataType='2' repHandlerStruct='' visible='true' inheritsFrom='' V281='13' V1='4' name='BASMG'>
            <structNode t='150' idref='1'/>
          </child>
          <child t='167' id='100' V167='21' V283='2' occurMinTimes='1' occurMaxTimes='1' minSize='-1' maxSize='-1' dataType='2' repHandlerStruct='' visible='true' inheritsFrom='' V281='13' V1='4' name='DZEIT'>
            <structNode t='150' idref='1'/>
          </child>
          <child t='167' id='101' V167='21' V283='2' occurMinTimes='1' occurMaxTimes='1' minSize='-1' maxSize='-1' dataType='2' repHandlerStruct='' visible='true' inheritsFrom='' V281='13' V1='4' name='MAXLZ'>
            <structNode t='150' idref='1'/>
          </child>
          <child t='167' id='102' V167='21' V283='2' occurMinTimes='1' occurMaxTimes='1' minSize='-1' maxSize='-1' dataType='2' repHandlerStruct='' visible='true' inheritsFrom='' V281='13' V1='4' name='UEETO'>
            <structNode t='150' idref='1'/>
          </child>
          <child t='167' id='103' V167='21' V283='2' occurMinTimes='1' occurMaxTimes='1' minSize='-1' maxSize='-1' dataType='2' repHandlerStruct='' visible='true' inheritsFrom='' V281='13' V1='4' name='UNETO'>
            <structNode t='150' idref='1'/>
          </child>
          <child t='167' id='104' V167='21' V283='2' occurMinTimes='1' occurMaxTimes='1' minSize='-1' maxSize='-1' dataType='2' repHandlerStruct='' visible='true' inheritsFrom='' V281='13' V1='4' name='WZEIT'>
            <structNode t='150' idref='1'/>
          </child>
          <child t='167' id='105' V167='21' V283='2' occurMinTimes='1' occurMaxTimes='1' minSize='-1' maxSize='-1' dataType='2' repHandlerStruct='' visible='true' inheritsFrom='' V281='13' V1='4' name='VZUSL'>
            <structNode t='150' idref='1'/>
          </child>
          <child t='167' id='106' V167='21' V283='2' occurMinTimes='1' occurMaxTimes='1' minSize='-1' maxSize='-1' dataType='2' repHandlerStruct='' visible='true' inheritsFrom='' V281='13' V1='4' name='UMLMC'>
            <structNode t='150' idref='1'/>
          </child>
          <child t='167' id='107' V167='21' V283='2' occurMinTimes='1' occurMaxTimes='1' minSize='-1' maxSize='-1' dataType='2' repHandlerStruct='' visible='true' inheritsFrom='' V281='13' V1='4' name='LADGR'>
            <structNode t='150' idref='1'/>
          </child>
          <child t='167' id='108' V167='21' V283='2' occurMinTimes='1' occurMaxTimes='1' minSize='-1' maxSize='-1' dataType='2' repHandlerStruct='' visible='true' inheritsFrom='' V281='13' V1='4' name='LGRAD'>
            <structNode t='150' idref='1'/>
          </child>
          <child t='167' id='109' V167='21' V283='2' occurMinTimes='1' occurMaxTimes='1' minSize='-1' maxSize='-1' dataType='2' repHandlerStruct='' visible='true' inheritsFrom='' V281='13' V1='4' name='OBJID'>
            <structNode t='150' idref='1'/>
          </child>
          <child t='167' id='110' V167='21' V283='2' occurMinTimes='1' occurMaxTimes='1' minSize='-1' maxSize='-1' dataType='2' repHandlerStruct='' visible='true' inheritsFrom='' V281='13' V1='4' name='VRVEZ'>
            <structNode t='150' idref='1'/>
          </child>
          <child t='167' id='111' V167='21' V283='2' occurMinTimes='1' occurMaxTimes='1' minSize='-1' maxSize='-1' dataType='2' repHandlerStruct='' visible='true' inheritsFrom='' V281='13' V1='4' name='VBAMG'>
            <structNode t='150' idref='1'/>
          </child>
          <child t='167' id='112' V167='21' V283='2' occurMinTimes='1' occurMaxTimes='1' minSize='-1' maxSize='-1' dataType='2' repHandlerStruct='' visible='true' inheritsFrom='' V281='13' V1='4' name='VBEAZ'>
            <structNode t='150' idref='1'/>
          </child>
          <child t='167' id='113' V167='21' V283='2' occurMinTimes='1' occurMaxTimes='1' minSize='-1' maxSize='-1' dataType='2' repHandlerStruct='' visible='true' inheritsFrom='' V281='13' V1='4' name='TRAME'>
            <structNode t='150' idref='1'/>
          </child>
          <child t='167' id='114' V167='21' V283='2' occurMinTimes='1' occurMaxTimes='1' minSize='-1' maxSize='-1' dataType='2' repHandlerStruct='' visible='true' inheritsFrom='' V281='13' V1='4' name='FXHOR'>
            <structNode t='150' idref='1'/>
          </child>
          <child t='167' id='115' V167='21' V283='2' occurMinTimes='1' occurMaxTimes='1' minSize='-1' maxSize='-1' dataType='2' repHandlerStruct='' visible='true' inheritsFrom='' V281='13' V1='4' name='VINT1'>
            <structNode t='150' idref='1'/>
          </child>
          <child t='167' id='116' V167='21' V283='2' occurMinTimes='1' occurMaxTimes='1' minSize='-1' maxSize='-1' dataType='2' repHandlerStruct='' visible='true' inheritsFrom='' V281='13' V1='4' name='VINT2'>
            <structNode t='150' idref='1'/>
          </child>
          <child t='167' id='117' V167='21' V283='2' occurMinTimes='1' occurMaxTimes='1' minSize='-1' maxSize='-1' dataType='2' repHandlerStruct='' visible='true' inheritsFrom='' V281='13' V1='4' name='LOSGR'>
            <structNode t='150' idref='1'/>
          </child>
          <child t='167' id='118' V167='21' V283='2' occurMinTimes='1' occurMaxTimes='1' minSize='-1' maxSize='-1' dataType='2' repHandlerStruct='' visible='true' inheritsFrom='' V281='13' V1='4' name='KAUSF'>
            <structNode t='150' idref='1'/>
          </child>
          <child t='167' id='119' V167='21' V283='2' occurMinTimes='1' occurMaxTimes='1' minSize='-1' maxSize='-1' dataType='2' repHandlerStruct='' visible='true' inheritsFrom='' V281='13' V1='4' name='TAKZT'>
            <structNode t='150' idref='1'/>
          </child>
          <child t='167' id='120' V167='21' V283='2' occurMinTimes='1' occurMaxTimes='1' minSize='-1' maxSize='-1' dataType='2' repHandlerStruct='' visible='true' inheritsFrom='' V281='13' V1='4' name='VRBDT'>
            <structNode t='150' idref='1'/>
          </child>
          <child t='167' id='121' V167='21' V283='2' occurMinTimes='1' occurMaxTimes='1' minSize='-1' maxSize='-1' dataType='2' repHandlerStruct='' visible='true' inheritsFrom='' V281='13' V1='4' name='VRBFK'>
            <structNode t='150' idref='1'/>
          </child>
          <child t='167' id='122' V167='21' V283='2' occurMinTimes='1' occurMaxTimes='1' minSize='-1' maxSize='-1' dataType='2' repHandlerStruct='' visible='true' inheritsFrom='' V281='13' V1='4' name='PREND'>
            <structNode t='150' idref='1'/>
          </child>
          <child t='167' id='123' V167='21' V283='2' occurMinTimes='1' occurMaxTimes='1' minSize='-1' maxSize='-1' dataType='2' repHandlerStruct='' visible='true' inheritsFrom='' V281='13' V1='4' name='PRENG'>
            <structNode t='150' idref='1'/>
          </child>
          <child t='167' id='124' V167='21' V283='2' occurMinTimes='1' occurMaxTimes='1' minSize='-1' maxSize='-1' dataType='2' repHandlerStruct='' visible='true' inheritsFrom='' V281='13' V1='4' name='PRFRQ'>
            <structNode t='150' idref='1'/>
          </child>
          <child t='167' id='125' V167='21' V283='2' occurMinTimes='1' occurMaxTimes='1' minSize='-1' maxSize='-1' dataType='2' repHandlerStruct='' visible='true' inheritsFrom='' V281='13' V1='4' name='SHZET'>
            <structNode t='150' idref='1'/>
          </child>
          <child t='167' id='126' V167='21' V283='2' occurMinTimes='1' occurMaxTimes='1' minSize='-1' maxSize='-1' dataType='2' repHandlerStruct='' visible='true' inheritsFrom='' V281='13' V1='4' name='MMSTD'>
            <structNode t='150' idref='1'/>
          </child>
          <child t='167' id='127' V167='21' V283='2' occurMinTimes='1' occurMaxTimes='1' minSize='-1' maxSize='-1' dataType='2' repHandlerStruct='' visible='true' inheritsFrom='' V281='13' V1='4' name='DPLHO'>
            <structNode t='150' idref='1'/>
          </child>
          <child t='167' id='128' V167='21' V283='2' occurMinTimes='1' occurMaxTimes='1' minSize='-1' maxSize='-1' dataType='2' repHandlerStruct='' visible='true' inheritsFrom='' V281='13' V1='4' name='MINLS'>
            <structNode t='150' idref='1'/>
          </child>
          <child t='167' id='129' V167='21' V283='2' occurMinTimes='1' occurMaxTimes='1' minSize='-1' maxSize='-1' dataType='2' repHandlerStruct='' visible='true' inheritsFrom='' V281='13' V1='4' name='MAXLS'>
            <structNode t='150' idref='1'/>
          </child>
          <child t='167' id='130' V167='21' V283='2' occurMinTimes='1' occurMaxTimes='1' minSize='-1' maxSize='-1' dataType='2' repHandlerStruct='' visible='true' inheritsFrom='' V281='13' V1='4' name='FIXLS'>
            <structNode t='150' idref='1'/>
          </child>
          <child t='167' id='131' V167='21' V283='2' occurMinTimes='1' occurMaxTimes='1' minSize='-1' maxSize='-1' dataType='2' repHandlerStruct='' visible='true' inheritsFrom='' V281='13' V1='4' name='LTINC'>
            <structNode t='150' idref='1'/>
          </child>
          <child t='167' id='132' V167='21' V283='2' occurMinTimes='1' occurMaxTimes='1' minSize='-1' maxSize='-1' dataType='2' repHandlerStruct='' visible='true' inheritsFrom='' V281='13' V1='4' name='COMPL'>
            <structNode t='150' idref='1'/>
          </child>
          <child t='167' id='133' V167='21' V283='2' occurMinTimes='1' occurMaxTimes='1' minSize='-1' maxSize='-1' dataType='2' repHandlerStruct='' visible='true' inheritsFrom='' V281='13' V1='4' name='EISLO'>
            <structNode t='150' idref='1'/>
          </child>
        </child>
        <child t='167' id='134' V167='21' V283='2' occurMinTimes='1' occurMaxTimes='1' minSize='-1' maxSize='-1' groupType='1' repHandlerStruct='' visible='true' inheritsFrom='' V281='13' V1='4' name='E1MARMM' checksumValid='true' checksum='SlAHEY0iW4cp9RylVSkik33Yd44='>
          <structNode t='150' idref='1'/>
          <child t='167' id='135' V167='21' V283='2' occurMaxTimes='1' minSize='-1' maxSize='-1' groupType='3' repHandlerStruct='' inheritsFrom='' V281='13' V1='4' name='Attributes'>
            <structNode t='150' idref='1'/>
            <child t='167' id='136' V167='21' V283='2' occurMinTimes='1' occurMaxTimes='1' minSize='-1' maxSize='-1' dataType='2' elemType='1' repHandlerStruct='' visible='true' inheritsFrom='' V281='13' V1='4' name='SEGMENT'>
              <structNode t='150' idref='1'/>
            </child>
          </child>
          <child t='167' id='137' V167='21' V283='2' occurMinTimes='1' occurMaxTimes='1' minSize='-1' maxSize='-1' dataType='2' repHandlerStruct='' visible='true' inheritsFrom='' V281='13' V1='4' name='MSGFN'>
            <structNode t='150' idref='1'/>
          </child>
          <child t='167' id='138' V167='21' V283='2' occurMinTimes='1' occurMaxTimes='1' minSize='-1' maxSize='-1' dataType='2' repHandlerStruct='' visible='true' inheritsFrom='' V281='13' V1='4' name='MEINH'>
            <structNode t='150' idref='1'/>
          </child>
          <child t='167' id='139' V167='21' V283='2' occurMinTimes='1' occurMaxTimes='1' minSize='-1' maxSize='-1' dataType='2' repHandlerStruct='' visible='true' inheritsFrom='' V281='13' V1='4' name='UMREZ'>
            <structNode t='150' idref='1'/>
          </child>
          <child t='167' id='140' V167='21' V283='2' occurMinTimes='1' occurMaxTimes='1' minSize='-1' maxSize='-1' dataType='2' repHandlerStruct='' visible='true' inheritsFrom='' V281='13' V1='4' name='UMREN'>
            <structNode t='150' idref='1'/>
          </child>
          <child t='167' id='141' V167='21' V283='2' occurMinTimes='1' occurMaxTimes='1' minSize='-1' maxSize='-1' dataType='2' repHandlerStruct='' visible='true' inheritsFrom='' V281='13' V1='4' name='LAENG'>
            <structNode t='150' idref='1'/>
          </child>
          <child t='167' id='142' V167='21' V283='2' occurMinTimes='1' occurMaxTimes='1' minSize='-1' maxSize='-1' dataType='2' repHandlerStruct='' visible='true' inheritsFrom='' V281='13' V1='4' name='BREIT'>
            <structNode t='150' idref='1'/>
          </child>
          <child t='167' id='143' V167='21' V283='2' occurMinTimes='1' occurMaxTimes='1' minSize='-1' maxSize='-1' dataType='2' repHandlerStruct='' visible='true' inheritsFrom='' V281='13' V1='4' name='HOEHE'>
            <structNode t='150' idref='1'/>
          </child>
          <child t='167' id='144' V167='21' V283='2' occurMinTimes='1' occurMaxTimes='1' minSize='-1' maxSize='-1' dataType='2' repHandlerStruct='' visible='true' inheritsFrom='' V281='13' V1='4' name='VOLUM'>
            <structNode t='150' idref='1'/>
          </child>
          <child t='167' id='145' V167='21' V283='2' occurMinTimes='1' occurMaxTimes='1' minSize='-1' maxSize='-1' dataType='2' repHandlerStruct='' visible='true' inheritsFrom='' V281='13' V1='4' name='BRGEW'>
            <structNode t='150' idref='1'/>
          </child>
          <child t='167' id='146' V167='21' V283='2' occurMinTimes='1' occurMaxTimes='1' minSize='-1' maxSize='-1' dataType='2' repHandlerStruct='' visible='true' inheritsFrom='' V281='13' V1='4' name='GEWEI'>
            <structNode t='150' idref='1'/>
          </child>
          <child t='167' id='147' V167='21' V283='2' occurMinTimes='1' occurMaxTimes='1' minSize='-1' maxSize='-1' dataType='2' repHandlerStruct='' visible='true' inheritsFrom='' V281='13' V1='4' name='NEST_FTR'>
            <structNode t='150' idref='1'/>
          </child>
          <child t='167' id='148' V167='21' V283='2' occurMinTimes='1' occurMaxTimes='1' minSize='-1' maxSize='-1' dataType='2' repHandlerStruct='' visible='true' inheritsFrom='' V281='13' V1='4' name='MAX_STACK'>
            <structNode t='150' idref='1'/>
          </child>
          <child t='167' id='149' V167='21' V283='2' occurMinTimes='1' occurMaxTimes='1' minSize='-1' maxSize='-1' dataType='2' repHandlerStruct='' visible='true' inheritsFrom='' V281='13' V1='4' name='CAPAUSE'>
            <structNode t='150' idref='1'/>
          </child>
        </child>
        <child t='167' id='150' V167='21' V283='2' occurMinTimes='1' occurMaxTimes='1' minSize='-1' maxSize='-1' groupType='1' repHandlerStruct='' visible='true' inheritsFrom='' V281='13' V1='4' name='E1MBEWM' checksumValid='true' checksum='dF8IRnkEhkvOhtjq0GZCa75kkHo='>
          <structNode t='150' idref='1'/>
          <child t='167' id='151' V167='21' V283='2' occurMaxTimes='1' minSize='-1' maxSize='-1' groupType='3' repHandlerStruct='' inheritsFrom='' V281='13' V1='4' name='Attributes'>
            <structNode t='150' idref='1'/>
            <child t='167' id='152' V167='21' V283='2' occurMinTimes='1' occurMaxTimes='1' minSize='-1' maxSize='-1' dataType='2' elemType='1' repHandlerStruct='' visible='true' inheritsFrom='' V281='13' V1='4' name='SEGMENT'>
              <structNode t='150' idref='1'/>
            </child>
          </child>
          <child t='167' id='153' V167='21' V283='2' occurMinTimes='1' occurMaxTimes='1' minSize='-1' maxSize='-1' dataType='2' repHandlerStruct='' visible='true' inheritsFrom='' V281='13' V1='4' name='MSGFN'>
            <structNode t='150' idref='1'/>
          </child>
          <child t='167' id='154' V167='21' V283='2' occurMinTimes='1' occurMaxTimes='1' minSize='-1' maxSize='-1' dataType='2' repHandlerStruct='' visible='true' inheritsFrom='' V281='13' V1='4' name='BWKEY'>
            <structNode t='150' idref='1'/>
          </child>
          <child t='167' id='155' V167='21' V283='2' occurMinTimes='1' occurMaxTimes='1' minSize='-1' maxSize='-1' dataType='2' repHandlerStruct='' visible='true' inheritsFrom='' V281='13' V1='4' name='VPRSV'>
            <structNode t='150' idref='1'/>
          </child>
          <child t='167' id='156' V167='21' V283='2' occurMinTimes='1' occurMaxTimes='1' minSize='-1' maxSize='-1' dataType='2' repHandlerStruct='' visible='true' inheritsFrom='' V281='13' V1='4' name='VERPR'>
            <structNode t='150' idref='1'/>
          </child>
          <child t='167' id='157' V167='21' V283='2' occurMinTimes='1' occurMaxTimes='1' minSize='-1' maxSize='-1' dataType='2' repHandlerStruct='' visible='true' inheritsFrom='' V281='13' V1='4' name='STPRS'>
            <structNode t='150' idref='1'/>
          </child>
          <child t='167' id='158' V167='21' V283='2' occurMinTimes='1' occurMaxTimes='1' minSize='-1' maxSize='-1' dataType='2' repHandlerStruct='' visible='true' inheritsFrom='' V281='13' V1='4' name='PEINH'>
            <structNode t='150' idref='1'/>
          </child>
          <child t='167' id='159' V167='21' V283='2' occurMinTimes='1' occurMaxTimes='1' minSize='-1' maxSize='-1' dataType='2' repHandlerStruct='' visible='true' inheritsFrom='' V281='13' V1='4' name='BKLAS'>
            <structNode t='150' idref='1'/>
          </child>
          <child t='167' id='160' V167='21' V283='2' occurMinTimes='1' occurMaxTimes='1' minSize='-1' maxSize='-1' dataType='2' repHandlerStruct='' visible='true' inheritsFrom='' V281='13' V1='4' name='VMVPR'>
            <structNode t='150' idref='1'/>
          </child>
          <child t='167' id='161' V167='21' V283='2' occurMinTimes='1' occurMaxTimes='1' minSize='-1' maxSize='-1' dataType='2' repHandlerStruct='' visible='true' inheritsFrom='' V281='13' V1='4' name='VMVER'>
            <structNode t='150' idref='1'/>
          </child>
          <child t='167' id='162' V167='21' V283='2' occurMinTimes='1' occurMaxTimes='1' minSize='-1' maxSize='-1' dataType='2' repHandlerStruct='' visible='true' inheritsFrom='' V281='13' V1='4' name='VMSTP'>
            <structNode t='150' idref='1'/>
          </child>
          <child t='167' id='163' V167='21' V283='2' occurMinTimes='1' occurMaxTimes='1' minSize='-1' maxSize='-1' dataType='2' repHandlerStruct='' visible='true' inheritsFrom='' V281='13' V1='4' name='VMPEI'>
            <structNode t='150' idref='1'/>
          </child>
          <child t='167' id='164' V167='21' V283='2' occurMinTimes='1' occurMaxTimes='1' minSize='-1' maxSize='-1' dataType='2' repHandlerStruct='' visible='true' inheritsFrom='' V281='13' V1='4' name='VMBKL'>
            <structNode t='150' idref='1'/>
          </child>
          <child t='167' id='165' V167='21' V283='2' occurMinTimes='1' occurMaxTimes='1' minSize='-1' maxSize='-1' dataType='2' repHandlerStruct='' visible='true' inheritsFrom='' V281='13' V1='4' name='VJVPR'>
            <structNode t='150' idref='1'/>
          </child>
          <child t='167' id='166' V167='21' V283='2' occurMinTimes='1' occurMaxTimes='1' minSize='-1' maxSize='-1' dataType='2' repHandlerStruct='' visible='true' inheritsFrom='' V281='13' V1='4' name='VJVER'>
            <structNode t='150' idref='1'/>
          </child>
          <child t='167' id='167' V167='21' V283='2' occurMinTimes='1' occurMaxTimes='1' minSize='-1' maxSize='-1' dataType='2' repHandlerStruct='' visible='true' inheritsFrom='' V281='13' V1='4' name='VJSTP'>
            <structNode t='150' idref='1'/>
          </child>
          <child t='167' id='168' V167='21' V283='2' occurMinTimes='1' occurMaxTimes='1' minSize='-1' maxSize='-1' dataType='2' repHandlerStruct='' visible='true' inheritsFrom='' V281='13' V1='4' name='LFGJA'>
            <structNode t='150' idref='1'/>
          </child>
          <child t='167' id='169' V167='21' V283='2' occurMinTimes='1' occurMaxTimes='1' minSize='-1' maxSize='-1' dataType='2' repHandlerStruct='' visible='true' inheritsFrom='' V281='13' V1='4' name='LFMON'>
            <structNode t='150' idref='1'/>
          </child>
          <child t='167' id='170' V167='21' V283='2' occurMinTimes='1' occurMaxTimes='1' minSize='-1' maxSize='-1' dataType='2' repHandlerStruct='' visible='true' inheritsFrom='' V281='13' V1='4' name='ZKPRS'>
            <structNode t='150' idref='1'/>
          </child>
          <child t='167' id='171' V167='21' V283='2' occurMinTimes='1' occurMaxTimes='1' minSize='-1' maxSize='-1' dataType='2' repHandlerStruct='' visible='true' inheritsFrom='' V281='13' V1='4' name='ZKDAT'>
            <structNode t='150' idref='1'/>
          </child>
          <child t='167' id='172' V167='21' V283='2' occurMinTimes='1' occurMaxTimes='1' minSize='-1' maxSize='-1' dataType='2' repHandlerStruct='' visible='true' inheritsFrom='' V281='13' V1='4' name='BWPRS'>
            <structNode t='150' idref='1'/>
          </child>
          <child t='167' id='173' V167='21' V283='2' occurMinTimes='1' occurMaxTimes='1' minSize='-1' maxSize='-1' dataType='2' repHandlerStruct='' visible='true' inheritsFrom='' V281='13' V1='4' name='BWPRH'>
            <structNode t='150' idref='1'/>
          </child>
          <child t='167' id='174' V167='21' V283='2' occurMinTimes='1' occurMaxTimes='1' minSize='-1' maxSize='-1' dataType='2' repHandlerStruct='' visible='true' inheritsFrom='' V281='13' V1='4' name='VJBWS'>
            <structNode t='150' idref='1'/>
          </child>
          <child t='167' id='175' V167='21' V283='2' occurMinTimes='1' occurMaxTimes='1' minSize='-1' maxSize='-1' dataType='2' repHandlerStruct='' visible='true' inheritsFrom='' V281='13' V1='4' name='VJBWH'>
            <structNode t='150' idref='1'/>
          </child>
          <child t='167' id='176' V167='21' V283='2' occurMinTimes='1' occurMaxTimes='1' minSize='-1' maxSize='-1' dataType='2' repHandlerStruct='' visible='true' inheritsFrom='' V281='13' V1='4' name='VVJLB'>
            <structNode t='150' idref='1'/>
          </child>
          <child t='167' id='177' V167='21' V283='2' occurMinTimes='1' occurMaxTimes='1' minSize='-1' maxSize='-1' dataType='2' repHandlerStruct='' visible='true' inheritsFrom='' V281='13' V1='4' name='VVMLB'>
            <structNode t='150' idref='1'/>
          </child>
          <child t='167' id='178' V167='21' V283='2' occurMinTimes='1' occurMaxTimes='1' minSize='-1' maxSize='-1' dataType='2' repHandlerStruct='' visible='true' inheritsFrom='' V281='13' V1='4' name='VVSAL'>
            <structNode t='150' idref='1'/>
          </child>
          <child t='167' id='179' V167='21' V283='2' occurMinTimes='1' occurMaxTimes='1' minSize='-1' maxSize='-1' dataType='2' repHandlerStruct='' visible='true' inheritsFrom='' V281='13' V1='4' name='ZPLPR'>
            <structNode t='150' idref='1'/>
          </child>
          <child t='167' id='180' V167='21' V283='2' occurMinTimes='1' occurMaxTimes='1' minSize='-1' maxSize='-1' dataType='2' repHandlerStruct='' visible='true' inheritsFrom='' V281='13' V1='4' name='ZPLP1'>
            <structNode t='150' idref='1'/>
          </child>
          <child t='167' id='181' V167='21' V283='2' occurMinTimes='1' occurMaxTimes='1' minSize='-1' maxSize='-1' dataType='2' repHandlerStruct='' visible='true' inheritsFrom='' V281='13' V1='4' name='ZPLP2'>
            <structNode t='150' idref='1'/>
          </child>
          <child t='167' id='182' V167='21' V283='2' occurMinTimes='1' occurMaxTimes='1' minSize='-1' maxSize='-1' dataType='2' repHandlerStruct='' visible='true' inheritsFrom='' V281='13' V1='4' name='ZPLP3'>
            <structNode t='150' idref='1'/>
          </child>
          <child t='167' id='183' V167='21' V283='2' occurMinTimes='1' occurMaxTimes='1' minSize='-1' maxSize='-1' dataType='2' repHandlerStruct='' visible='true' inheritsFrom='' V281='13' V1='4' name='ZPLD1'>
            <structNode t='150' idref='1'/>
          </child>
          <child t='167' id='184' V167='21' V283='2' occurMinTimes='1' occurMaxTimes='1' minSize='-1' maxSize='-1' dataType='2' repHandlerStruct='' visible='true' inheritsFrom='' V281='13' V1='4' name='ZPLD2'>
            <structNode t='150' idref='1'/>
          </child>
          <child t='167' id='185' V167='21' V283='2' occurMinTimes='1' occurMaxTimes='1' minSize='-1' maxSize='-1' dataType='2' repHandlerStruct='' visible='true' inheritsFrom='' V281='13' V1='4' name='ZPLD3'>
            <structNode t='150' idref='1'/>
          </child>
          <child t='167' id='186' V167='21' V283='2' occurMinTimes='1' occurMaxTimes='1' minSize='-1' maxSize='-1' dataType='2' repHandlerStruct='' visible='true' inheritsFrom='' V281='13' V1='4' name='BWPH1'>
            <structNode t='150' idref='1'/>
          </child>
          <child t='167' id='187' V167='21' V283='2' occurMinTimes='1' occurMaxTimes='1' minSize='-1' maxSize='-1' dataType='2' repHandlerStruct='' visible='true' inheritsFrom='' V281='13' V1='4' name='BWPS1'>
            <structNode t='150' idref='1'/>
          </child>
          <child t='167' id='188' V167='21' V283='2' occurMinTimes='1' occurMaxTimes='1' minSize='-1' maxSize='-1' dataType='2' repHandlerStruct='' visible='true' inheritsFrom='' V281='13' V1='4' name='ABWKZ'>
            <structNode t='150' idref='1'/>
          </child>
          <child t='167' id='189' V167='21' V283='2' occurMinTimes='1' occurMaxTimes='1' minSize='-1' maxSize='-1' dataType='2' repHandlerStruct='' visible='true' inheritsFrom='' V281='13' V1='4' name='PSTAT'>
            <structNode t='150' idref='1'/>
          </child>
          <child t='167' id='190' V167='21' V283='2' occurMinTimes='1' occurMaxTimes='1' minSize='-1' maxSize='-1' dataType='2' repHandlerStruct='' visible='true' inheritsFrom='' V281='13' V1='4' name='KALN1'>
            <structNode t='150' idref='1'/>
          </child>
          <child t='167' id='191' V167='21' V283='2' occurMinTimes='1' occurMaxTimes='1' minSize='-1' maxSize='-1' dataType='2' repHandlerStruct='' visible='true' inheritsFrom='' V281='13' V1='4' name='KALNR'>
            <structNode t='150' idref='1'/>
          </child>
          <child t='167' id='192' V167='21' V283='2' occurMinTimes='1' occurMaxTimes='1' minSize='-1' maxSize='-1' dataType='2' repHandlerStruct='' visible='true' inheritsFrom='' V281='13' V1='4' name='VERS1'>
            <structNode t='150' idref='1'/>
          </child>
          <child t='167' id='193' V167='21' V283='2' occurMinTimes='1' occurMaxTimes='1' minSize='-1' maxSize='-1' dataType='2' repHandlerStruct='' visible='true' inheritsFrom='' V281='13' V1='4' name='VERS2'>
            <structNode t='150' idref='1'/>
          </child>
          <child t='167' id='194' V167='21' V283='2' occurMinTimes='1' occurMaxTimes='1' minSize='-1' maxSize='-1' dataType='2' repHandlerStruct='' visible='true' inheritsFrom='' V281='13' V1='4' name='VERS3'>
            <structNode t='150' idref='1'/>
          </child>
          <child t='167' id='195' V167='21' V283='2' occurMinTimes='1' occurMaxTimes='1' minSize='-1' maxSize='-1' dataType='2' repHandlerStruct='' visible='true' inheritsFrom='' V281='13' V1='4' name='PPRDZ'>
            <structNode t='150' idref='1'/>
          </child>
          <child t='167' id='196' V167='21' V283='2' occurMinTimes='1' occurMaxTimes='1' minSize='-1' maxSize='-1' dataType='2' repHandlerStruct='' visible='true' inheritsFrom='' V281='13' V1='4' name='PPRDL'>
            <structNode t='150' idref='1'/>
          </child>
          <child t='167' id='197' V167='21' V283='2' occurMinTimes='1' occurMaxTimes='1' minSize='-1' maxSize='-1' dataType='2' repHandlerStruct='' visible='true' inheritsFrom='' V281='13' V1='4' name='PPRDV'>
            <structNode t='150' idref='1'/>
          </child>
          <child t='167' id='198' V167='21' V283='2' occurMinTimes='1' occurMaxTimes='1' minSize='-1' maxSize='-1' dataType='2' repHandlerStruct='' visible='true' inheritsFrom='' V281='13' V1='4' name='PDATZ'>
            <structNode t='150' idref='1'/>
          </child>
          <child t='167' id='199' V167='21' V283='2' occurMinTimes='1' occurMaxTimes='1' minSize='-1' maxSize='-1' dataType='2' repHandlerStruct='' visible='true' inheritsFrom='' V281='13' V1='4' name='PDATL'>
            <structNode t='150' idref='1'/>
          </child>
          <child t='167' id='200' V167='21' V283='2' occurMinTimes='1' occurMaxTimes='1' minSize='-1' maxSize='-1' dataType='2' repHandlerStruct='' visible='true' inheritsFrom='' V281='13' V1='4' name='PDATV'>
            <structNode t='150' idref='1'/>
          </child>
          <child t='167' id='201' V167='21' V283='2' occurMinTimes='1' occurMaxTimes='1' minSize='-1' maxSize='-1' dataType='2' repHandlerStruct='' visible='true' inheritsFrom='' V281='13' V1='4' name='VPLPR'>
            <structNode t='150' idref='1'/>
          </child>
          <child t='167' id='202' V167='21' V283='2' occurMinTimes='1' occurMaxTimes='1' minSize='-1' maxSize='-1' dataType='2' repHandlerStruct='' visible='true' inheritsFrom='' V281='13' V1='4' name='MLMAA'>
            <structNode t='150' idref='1'/>
          </child>
          <child t='167' id='203' V167='21' V283='2' occurMinTimes='1' occurMaxTimes='1' minSize='-1' maxSize='-1' dataType='2' repHandlerStruct='' visible='true' inheritsFrom='' V281='13' V1='4' name='MLAST'>
            <structNode t='150' idref='1'/>
          </child>
          <child t='167' id='204' V167='21' V283='2' occurMinTimes='1' occurMaxTimes='1' minSize='-1' maxSize='-1' dataType='2' repHandlerStruct='' visible='true' inheritsFrom='' V281='13' V1='4' name='VJBKL'>
            <structNode t='150' idref='1'/>
          </child>
          <child t='167' id='205' V167='21' V283='2' occurMinTimes='1' occurMaxTimes='1' minSize='-1' maxSize='-1' dataType='2' repHandlerStruct='' visible='true' inheritsFrom='' V281='13' V1='4' name='VJPEI'>
            <structNode t='150' idref='1'/>
          </child>
          <child t='167' id='206' V167='21' V283='2' occurMinTimes='1' occurMaxTimes='1' minSize='-1' maxSize='-1' dataType='2' repHandlerStruct='' visible='true' inheritsFrom='' V281='13' V1='4' name='BWPEI'>
            <structNode t='150' idref='1'/>
          </child>
        </child>
        <child t='167' id='207' V167='21' V283='2' occurMinTimes='1' occurMaxTimes='1' minSize='-1' maxSize='-1' groupType='1' repHandlerStruct='' visible='true' inheritsFrom='' V281='13' V1='4' name='E1MVKEM' checksumValid='true' checksum='dxeBkZw1aqCiR5BetWY01j0pF4A='>
          <structNode t='150' idref='1'/>
          <child t='167' id='208' V167='21' V283='2' occurMaxTimes='1' minSize='-1' maxSize='-1' groupType='3' repHandlerStruct='' inheritsFrom='' V281='13' V1='4' name='Attributes'>
            <structNode t='150' idref='1'/>
            <child t='167' id='209' V167='21' V283='2' occurMinTimes='1' occurMaxTimes='1' minSize='-1' maxSize='-1' dataType='2' elemType='1' repHandlerStruct='' visible='true' inheritsFrom='' V281='13' V1='4' name='SEGMENT'>
              <structNode t='150' idref='1'/>
            </child>
          </child>
          <child t='167' id='210' V167='21' V283='2' occurMinTimes='1' occurMaxTimes='1' minSize='-1' maxSize='-1' dataType='2' repHandlerStruct='' visible='true' inheritsFrom='' V281='13' V1='4' name='MSGFN'>
            <structNode t='150' idref='1'/>
          </child>
          <child t='167' id='211' V167='21' V283='2' occurMinTimes='1' occurMaxTimes='1' minSize='-1' maxSize='-1' dataType='2' repHandlerStruct='' visible='true' inheritsFrom='' V281='13' V1='4' name='VKORG'>
            <structNode t='150' idref='1'/>
          </child>
          <child t='167' id='212' V167='21' V283='2' occurMinTimes='1' occurMaxTimes='1' minSize='-1' maxSize='-1' dataType='2' repHandlerStruct='' visible='true' inheritsFrom='' V281='13' V1='4' name='VTWEG'>
            <structNode t='150' idref='1'/>
          </child>
          <child t='167' id='213' V167='21' V283='2' occurMinTimes='1' occurMaxTimes='1' minSize='-1' maxSize='-1' dataType='2' repHandlerStruct='' visible='true' inheritsFrom='' V281='13' V1='4' name='SKTOF'>
            <structNode t='150' idref='1'/>
          </child>
          <child t='167' id='214' V167='21' V283='2' occurMinTimes='1' occurMaxTimes='1' minSize='-1' maxSize='-1' dataType='2' repHandlerStruct='' visible='true' inheritsFrom='' V281='13' V1='4' name='VMSTD'>
            <structNode t='150' idref='1'/>
          </child>
          <child t='167' id='215' V167='21' V283='2' occurMinTimes='1' occurMaxTimes='1' minSize='-1' maxSize='-1' dataType='2' repHandlerStruct='' visible='true' inheritsFrom='' V281='13' V1='4' name='AUMNG'>
            <structNode t='150' idref='1'/>
          </child>
          <child t='167' id='216' V167='21' V283='2' occurMinTimes='1' occurMaxTimes='1' minSize='-1' maxSize='-1' dataType='2' repHandlerStruct='' visible='true' inheritsFrom='' V281='13' V1='4' name='LFMNG'>
            <structNode t='150' idref='1'/>
          </child>
          <child t='167' id='217' V167='21' V283='2' occurMinTimes='1' occurMaxTimes='1' minSize='-1' maxSize='-1' dataType='2' repHandlerStruct='' visible='true' inheritsFrom='' V281='13' V1='4' name='EFMNG'>
            <structNode t='150' idref='1'/>
          </child>
          <child t='167' id='218' V167='21' V283='2' occurMinTimes='1' occurMaxTimes='1' minSize='-1' maxSize='-1' dataType='2' repHandlerStruct='' visible='true' inheritsFrom='' V281='13' V1='4' name='SCMNG'>
            <structNode t='150' idref='1'/>
          </child>
          <child t='167' id='219' V167='21' V283='2' occurMinTimes='1' occurMaxTimes='1' minSize='-1' maxSize='-1' dataType='2' repHandlerStruct='' visible='true' inheritsFrom='' V281='13' V1='4' name='MTPOS'>
            <structNode t='150' idref='1'/>
          </child>
        </child>
        <child t='167' id='220' V167='21' V283='2' occurMinTimes='1' occurMaxTimes='1' minSize='-1' maxSize='-1' groupType='1' repHandlerStruct='' visible='true' inheritsFrom='' V281='13' V1='4' name='E1MLANM'>
          <structNode t='150' idref='1'/>
          <child t='167' id='221' V167='21' V283='2' occurMaxTimes='1' minSize='-1' maxSize='-1' groupType='3' repHandlerStruct='' inheritsFrom='' V281='13' V1='4' name='Attributes'>
            <structNode t='150' idref='1'/>
            <child t='167' id='222' V167='21' V283='2' occurMinTimes='1' occurMaxTimes='1' minSize='-1' maxSize='-1' dataType='2' elemType='1' repHandlerStruct='' visible='true' inheritsFrom='' V281='13' V1='4' name='SEGMENT'>
              <structNode t='150' idref='1'/>
            </child>
          </child>
          <child t='167' id='223' V167='21' V283='2' occurMinTimes='1' occurMaxTimes='1' minSize='-1' maxSize='-1' dataType='2' repHandlerStruct='' visible='true' inheritsFrom='' V281='13' V1='4' name='MSGFN'>
            <structNode t='150' idref='1'/>
          </child>
          <child t='167' id='224' V167='21' V283='2' occurMinTimes='1' occurMaxTimes='1' minSize='-1' maxSize='-1' dataType='2' repHandlerStruct='' visible='true' inheritsFrom='' V281='13' V1='4' name='ALAND'>
            <structNode t='150' idref='1'/>
          </child>
          <child t='167' id='225' V167='21' V283='2' occurMinTimes='1' occurMaxTimes='1' minSize='-1' maxSize='-1' dataType='2' repHandlerStruct='' visible='true' inheritsFrom='' V281='13' V1='4' name='TATY1'>
            <structNode t='150' idref='1'/>
          </child>
          <child t='167' id='226' V167='21' V283='2' occurMinTimes='1' occurMaxTimes='1' minSize='-1' maxSize='-1' dataType='2' repHandlerStruct='' visible='true' inheritsFrom='' V281='13' V1='4' name='TAXM1'>
            <structNode t='150' idref='1'/>
          </child>
        </child>
        <child t='167' id='227' V167='21' V283='2' occurMinTimes='1' occurMaxTimes='1' minSize='-1' maxSize='-1' groupType='1' repHandlerStruct='' visible='true' inheritsFrom='' V281='13' V1='4' name='E1MTXHM' checksumValid='true' checksum='x3PgmQPiLCZ13Vx3+g99VQfvg/M='>
          <structNode t='150' idref='1'/>
          <child t='167' id='228' V167='21' V283='2' occurMaxTimes='1' minSize='-1' maxSize='-1' groupType='3' repHandlerStruct='' inheritsFrom='' V281='13' V1='4' name='Attributes'>
            <structNode t='150' idref='1'/>
            <child t='167' id='229' V167='21' V283='2' occurMinTimes='1' occurMaxTimes='1' minSize='-1' maxSize='-1' dataType='2' elemType='1' repHandlerStruct='' visible='true' inheritsFrom='' V281='13' V1='4' name='SEGMENT'>
              <structNode t='150' idref='1'/>
            </child>
          </child>
          <child t='167' id='230' V167='21' V283='2' occurMinTimes='1' occurMaxTimes='1' minSize='-1' maxSize='-1' dataType='2' repHandlerStruct='' visible='true' inheritsFrom='' V281='13' V1='4' name='MSGFN'>
            <structNode t='150' idref='1'/>
          </child>
          <child t='167' id='231' V167='21' V283='2' occurMinTimes='1' occurMaxTimes='1' minSize='-1' maxSize='-1' dataType='2' repHandlerStruct='' visible='true' inheritsFrom='' V281='13' V1='4' name='TDOBJECT'>
            <structNode t='150' idref='1'/>
          </child>
          <child t='167' id='232' V167='21' V283='2' occurMinTimes='1' occurMaxTimes='1' minSize='-1' maxSize='-1' dataType='2' repHandlerStruct='' visible='true' inheritsFrom='' V281='13' V1='4' name='TDNAME'>
            <structNode t='150' idref='1'/>
          </child>
          <child t='167' id='233' V167='21' V283='2' occurMinTimes='1' occurMaxTimes='1' minSize='-1' maxSize='-1' dataType='2' repHandlerStruct='' visible='true' inheritsFrom='' V281='13' V1='4' name='TDID'>
            <structNode t='150' idref='1'/>
          </child>
          <child t='167' id='234' V167='21' V283='2' occurMinTimes='1' occurMaxTimes='1' minSize='-1' maxSize='-1' dataType='2' repHandlerStruct='' visible='true' inheritsFrom='' V281='13' V1='4' name='TDSPRAS'>
            <structNode t='150' idref='1'/>
          </child>
          <child t='167' id='235' V167='21' V283='2' occurMinTimes='1' occurMaxTimes='1' minSize='-1' maxSize='-1' dataType='2' repHandlerStruct='' visible='true' inheritsFrom='' V281='13' V1='4' name='TDTEXTTYPE'>
            <structNode t='150' idref='1'/>
          </child>
          <child t='167' id='236' V167='21' V283='2' occurMinTimes='1' occurMaxTimes='1' minSize='-1' maxSize='-1' dataType='2' repHandlerStruct='' visible='true' inheritsFrom='' V281='13' V1='4' name='SPRAS_ISO'>
            <structNode t='150' idref='1'/>
          </child>
          <child t='167' id='237' V167='21' V283='2' occurMinTimes='1' occurMaxTimes='1' minSize='-1' maxSize='-1' groupType='1' repHandlerStruct='' visible='true' inheritsFrom='' V281='13' V1='4' name='E1MTXLM'>
            <structNode t='150' idref='1'/>
            <child t='167' id='238' V167='21' V283='2' occurMaxTimes='1' minSize='-1' maxSize='-1' groupType='3' repHandlerStruct='' inheritsFrom='' V281='13' V1='4' name='Attributes'>
              <structNode t='150' idref='1'/>
              <child t='167' id='239' V167='21' V283='2' occurMinTimes='1' occurMaxTimes='1' minSize='-1' maxSize='-1' dataType='2' elemType='1' repHandlerStruct='' visible='true' inheritsFrom='' V281='13' V1='4' name='SEGMENT'>
                <structNode t='150' idref='1'/>
              </child>
            </child>
            <child t='167' id='240' V167='21' V283='2' occurMinTimes='1' occurMaxTimes='1' minSize='-1' maxSize='-1' dataType='2' repHandlerStruct='' visible='true' inheritsFrom='' V281='13' V1='4' name='MSGFN'>
              <structNode t='150' idref='1'/>
            </child>
            <child t='167' id='241' V167='21' V283='2' occurMinTimes='1' occurMaxTimes='1' minSize='-1' maxSize='-1' dataType='2' repHandlerStruct='' visible='true' inheritsFrom='' V281='13' V1='4' name='TDFORMAT'>
              <structNode t='150' idref='1'/>
            </child>
            <child t='167' id='242' V167='21' V283='2' occurMinTimes='1' occurMaxTimes='1' minSize='-1' maxSize='-1' dataType='2' repHandlerStruct='' visible='true' inheritsFrom='' V281='13' V1='4' name='TDLINE'>
              <structNode t='150' idref='1'/>
            </child>
          </child>
        </child>
      </child>
      <child t='167' id='243' V167='21' V283='2' occurMinTimes='1' occurMaxTimes='-1' minSize='-1' maxSize='-1' groupType='1' repHandlerStruct='' visible='true' inheritsFrom='' V281='13' V1='4' name='EDI_DS40' checksumValid='true' checksum='HE1u7owvZ1YGAVkrdBX+ojkrBZw='>
        <structNode t='150' idref='1'/>
        <child t='167' id='244' V167='21' V283='2' occurMaxTimes='1' minSize='-1' maxSize='-1' groupType='3' repHandlerStruct='' inheritsFrom='' V281='13' V1='4' name='Attributes'>
          <structNode t='150' idref='1'/>
          <child t='167' id='245' V167='21' V283='2' occurMinTimes='1' occurMaxTimes='1' minSize='-1' maxSize='-1' dataType='2' elemType='1' repHandlerStruct='' visible='true' inheritsFrom='' V281='13' V1='4' name='SEGMENT'>
            <structNode t='150' idref='1'/>
          </child>
        </child>
        <child t='167' id='246' V167='21' V283='2' occurMinTimes='1' occurMaxTimes='1' minSize='-1' maxSize='-1' dataType='2' repHandlerStruct='' visible='true' inheritsFrom='' V281='13' V1='4' name='MANDT'>
          <structNode t='150' idref='1'/>
        </child>
        <child t='167' id='247' V167='21' V283='2' occurMinTimes='1' occurMaxTimes='1' minSize='-1' maxSize='-1' dataType='2' repHandlerStruct='' visible='true' inheritsFrom='' V281='13' V1='4' name='DOCNUM'>
          <structNode t='150' idref='1'/>
        </child>
        <child t='167' id='248' V167='21' V283='2' occurMinTimes='1' occurMaxTimes='1' minSize='-1' maxSize='-1' dataType='2' repHandlerStruct='' visible='true' inheritsFrom='' V281='13' V1='4' name='LOGDAT'>
          <structNode t='150' idref='1'/>
        </child>
        <child t='167' id='249' V167='21' V283='2' occurMinTimes='1' occurMaxTimes='1' minSize='-1' maxSize='-1' dataType='2' repHandlerStruct='' visible='true' inheritsFrom='' V281='13' V1='4' name='LOGTIM'>
          <structNode t='150' idref='1'/>
        </child>
        <child t='167' id='250' V167='21' V283='2' occurMinTimes='1' occurMaxTimes='1' minSize='-1' maxSize='-1' dataType='2' repHandlerStruct='' visible='true' inheritsFrom='' V281='13' V1='4' name='STATUS'>
          <structNode t='150' idref='1'/>
        </child>
        <child t='167' id='251' V167='21' V283='2' occurMinTimes='1' occurMaxTimes='1' minSize='-1' maxSize='-1' dataType='2' repHandlerStruct='' visible='true' inheritsFrom='' V281='13' V1='4' name='STAMNO'>
          <structNode t='150' idref='1'/>
        </child>
        <child t='167' id='252' V167='21' V283='2' occurMinTimes='1' occurMaxTimes='1' minSize='-1' maxSize='-1' dataType='2' repHandlerStruct='' visible='true' inheritsFrom='' V281='13' V1='4' name='UNAME'>
          <structNode t='150' idref='1'/>
        </child>
        <child t='167' id='253' V167='21' V283='2' occurMinTimes='1' occurMaxTimes='1' minSize='-1' maxSize='-1' dataType='2' repHandlerStruct='' visible='true' inheritsFrom='' V281='13' V1='4' name='SEGNUM'>
          <structNode t='150' idref='1'/>
        </child>
      </child>
    </child>
  </rootElem>
  <defaultRep t='172' id='254' V172='6' autoFixNamespaceMismatch='true' V170='10' V692='1' unnamedElemsNamespace='1' V690='1' importDate='Tue Dec 22 13:07:17 AST 2020' importFile='file:/C:/Users/Palem.varun/Documents/IDoc/MATMAS01.xml' ignoreExcluded='true' fixInvalidCharacters='true' V1='4' name='XML'>
    <namespaceContainers t='220' ref='Namespace Containers/IDocs.xml'/>
  </defaultRep>
  <child t='162' id='255' V1='4' name='Representations'>
    <child t='172' idref='254'/>
  </child>
  <child t='165' id='256' V1='4' name='Document Bindings'>
  </child>
</root>
