<?xml version="1.0" encoding="UTF-8"?>
<root t='190' id='1' V190='11' inStruct='Structures/Tender_Fee_Test_Idoc.xml' outStruct='Structures/Jaggaer/IDocs/ZFIDCCP01.xml' inputRep='172' outputRep='181' nextMap='' inputStructUserName='Tender_Fee_Test_Idoc' outputStructUserName='ZFIDCCP01' V1='4' name='Tender_Fee' incarnation='797'>
  <inputMapElem t='200' id='4' V200='8' input='true' structElemExists='true' usedCount='5' V283='2' occurMinTimes='1' occurMaxTimes='1' minSize='-1' maxSize='-1' groupType='1' repHandlerStruct='' visible='true' inheritsFrom='' V281='13' V1='4' name='rootTag'>
    <mapNode t='190' idref='1'/>
    <child t='200' id='5' V200='8' input='true' structElemExists='true' V283='2' occurMinTimes='1' occurMaxTimes='1' minSize='-1' maxSize='-1' dataType='2' repHandlerStruct='' visible='true' inheritsFrom='' V281='13' V1='4' name='BLDAT'>
      <mapNode t='190' idref='1'/>
    </child>
    <child t='200' id='6' V200='8' input='true' structElemExists='true' usedCount='2' V283='2' occurMinTimes='1' occurMaxTimes='1' minSize='-1' maxSize='-1' dataType='2' repHandlerStruct='' visible='true' inheritsFrom='' V281='13' V1='4' name='BLART'>
      <mapNode t='190' idref='1'/>
    </child>
    <child t='200' id='7' V200='8' input='true' structElemExists='true' V283='2' occurMinTimes='1' occurMaxTimes='1' minSize='-1' maxSize='-1' dataType='2' repHandlerStruct='' visible='true' inheritsFrom='' V281='13' V1='4' name='BURKS'>
      <mapNode t='190' idref='1'/>
    </child>
    <child t='200' id='8' V200='8' input='true' structElemExists='true' V283='2' occurMinTimes='1' occurMaxTimes='1' minSize='-1' maxSize='-1' dataType='2' repHandlerStruct='' visible='true' inheritsFrom='' V281='13' V1='4' name='BUDAT'>
      <mapNode t='190' idref='1'/>
    </child>
    <child t='200' id='9' V200='8' input='true' structElemExists='true' V283='2' occurMinTimes='1' occurMaxTimes='1' minSize='-1' maxSize='-1' dataType='2' repHandlerStruct='' visible='true' inheritsFrom='' V281='13' V1='4' name='GJHAR'>
      <mapNode t='190' idref='1'/>
    </child>
    <child t='200' id='10' V200='8' input='true' structElemExists='true' V283='2' occurMinTimes='1' occurMaxTimes='1' minSize='-1' maxSize='-1' dataType='2' repHandlerStruct='' visible='true' inheritsFrom='' V281='13' V1='4' name='MONAT'>
      <mapNode t='190' idref='1'/>
    </child>
    <child t='200' id='11' V200='8' input='true' structElemExists='true' V283='2' occurMinTimes='1' occurMaxTimes='1' minSize='-1' maxSize='-1' dataType='2' repHandlerStruct='' visible='true' inheritsFrom='' V281='13' V1='4' name='WEARS'>
      <mapNode t='190' idref='1'/>
    </child>
    <child t='200' id='12' V200='8' input='true' structElemExists='true' V283='2' occurMinTimes='1' occurMaxTimes='1' minSize='-1' maxSize='-1' dataType='2' repHandlerStruct='' visible='true' inheritsFrom='' V281='13' V1='4' name='XBLNR'>
      <mapNode t='190' idref='1'/>
    </child>
    <child t='200' id='13' V200='8' input='true' structElemExists='true' V283='2' occurMinTimes='1' occurMaxTimes='1' minSize='-1' maxSize='-1' dataType='2' repHandlerStruct='' visible='true' inheritsFrom='' V281='13' V1='4' name='BKTXT'>
      <mapNode t='190' idref='1'/>
    </child>
    <child t='200' id='14' V200='8' input='true' structElemExists='true' V283='2' occurMinTimes='1' occurMaxTimes='1' minSize='-1' maxSize='-1' dataType='2' repHandlerStruct='' visible='true' inheritsFrom='' V281='13' V1='4' name='BSCHL'>
      <mapNode t='190' idref='1'/>
    </child>
    <child t='200' id='15' V200='8' input='true' structElemExists='true' V283='2' occurMinTimes='1' occurMaxTimes='1' minSize='-1' maxSize='-1' dataType='2' repHandlerStruct='' visible='true' inheritsFrom='' V281='13' V1='4' name='BUZEI'>
      <mapNode t='190' idref='1'/>
    </child>
    <child t='200' id='16' V200='8' input='true' structElemExists='true' V283='2' occurMinTimes='1' occurMaxTimes='1' minSize='-1' maxSize='-1' dataType='2' repHandlerStruct='' visible='true' inheritsFrom='' V281='13' V1='4' name='HKONT'>
      <mapNode t='190' idref='1'/>
    </child>
    <child t='200' id='17' V200='8' input='true' structElemExists='true' V283='2' occurMinTimes='1' occurMaxTimes='1' minSize='-1' maxSize='-1' dataType='2' repHandlerStruct='' visible='true' inheritsFrom='' V281='13' V1='4' name='DMBTR'>
      <mapNode t='190' idref='1'/>
    </child>
    <child t='200' id='18' V200='8' input='true' structElemExists='true' V283='2' occurMinTimes='1' occurMaxTimes='1' minSize='-1' maxSize='-1' dataType='2' repHandlerStruct='' visible='true' inheritsFrom='' V281='13' V1='4' name='SGTXT'>
      <mapNode t='190' idref='1'/>
    </child>
    <child t='200' id='19' V200='8' input='true' structElemExists='true' V283='2' occurMinTimes='1' occurMaxTimes='1' minSize='-1' maxSize='-1' dataType='2' repHandlerStruct='' visible='true' inheritsFrom='' V281='13' V1='4' name='GLVOR'>
      <mapNode t='190' idref='1'/>
    </child>
    <child t='200' id='20' V200='8' input='true' structElemExists='true' V283='2' occurMinTimes='1' occurMaxTimes='1' minSize='-1' maxSize='-1' dataType='2' repHandlerStruct='' visible='true' inheritsFrom='' V281='13' V1='4' name='KOART'>
      <mapNode t='190' idref='1'/>
    </child>
    <child t='200' id='21' V200='8' input='true' structElemExists='true' V283='2' occurMinTimes='1' occurMaxTimes='1' minSize='-1' maxSize='-1' dataType='2' repHandlerStruct='' visible='true' inheritsFrom='' V281='13' V1='4' name='SHKZG'>
      <mapNode t='190' idref='1'/>
    </child>
    <child t='200' id='22' V200='8' input='true' structElemExists='true' V283='2' occurMinTimes='1' occurMaxTimes='1' minSize='-1' maxSize='-1' dataType='2' repHandlerStruct='' visible='true' inheritsFrom='' V281='13' V1='4' name='VALUT'>
      <mapNode t='190' idref='1'/>
    </child>
    <child t='200' id='23' V200='8' input='true' structElemExists='true' V283='2' occurMinTimes='1' occurMaxTimes='1' minSize='-1' maxSize='-1' dataType='2' repHandlerStruct='' visible='true' inheritsFrom='' V281='13' V1='4' name='ZUONR'>
      <mapNode t='190' idref='1'/>
    </child>
    <child t='200' id='24' V200='8' input='true' structElemExists='true' V283='2' occurMinTimes='1' occurMaxTimes='1' minSize='-1' maxSize='-1' dataType='2' repHandlerStruct='' visible='true' inheritsFrom='' V281='13' V1='4' name='LIFNR'>
      <mapNode t='190' idref='1'/>
    </child>
    <child t='200' id='25' V200='8' input='true' structElemExists='true' V283='2' occurMinTimes='1' occurMaxTimes='1' minSize='-1' maxSize='-1' dataType='2' repHandlerStruct='' visible='true' inheritsFrom='' V281='13' V1='4' name='VORGN'>
      <mapNode t='190' idref='1'/>
    </child>
    <child t='200' id='26' V200='8' input='true' structElemExists='true' V283='2' occurMinTimes='1' occurMaxTimes='1' minSize='-1' maxSize='-1' dataType='2' repHandlerStruct='' visible='true' inheritsFrom='' V281='13' V1='4' name='KOKRS'>
      <mapNode t='190' idref='1'/>
    </child>
    <child t='200' id='27' V200='8' input='true' structElemExists='true' V283='2' occurMinTimes='1' occurMaxTimes='1' minSize='-1' maxSize='-1' dataType='2' repHandlerStruct='' visible='true' inheritsFrom='' V281='13' V1='4' name='FDLEV'>
      <mapNode t='190' idref='1'/>
    </child>
    <child t='200' id='28' V200='8' input='true' structElemExists='true' V283='2' occurMinTimes='1' occurMaxTimes='1' minSize='-1' maxSize='-1' dataType='2' repHandlerStruct='' visible='true' inheritsFrom='' V281='13' V1='4' name='FDGRP'>
      <mapNode t='190' idref='1'/>
    </child>
    <child t='200' id='29' V200='8' input='true' structElemExists='true' V283='2' occurMinTimes='1' occurMaxTimes='1' minSize='-1' maxSize='-1' dataType='2' repHandlerStruct='' visible='true' inheritsFrom='' V281='13' V1='4' name='FDTAG'>
      <mapNode t='190' idref='1'/>
    </child>
    <child t='200' id='30' V200='8' input='true' structElemExists='true' V283='2' occurMinTimes='1' occurMaxTimes='1' minSize='-1' maxSize='-1' dataType='2' repHandlerStruct='' visible='true' inheritsFrom='' V281='13' V1='4' name='ZFBDT'>
      <mapNode t='190' idref='1'/>
    </child>
    <child t='200' id='31' V200='8' input='true' structElemExists='true' V283='2' occurMinTimes='1' occurMaxTimes='1' minSize='-1' maxSize='-1' dataType='2' repHandlerStruct='' visible='true' inheritsFrom='' V281='13' V1='4' name='ZTERM'>
      <mapNode t='190' idref='1'/>
    </child>
    <child t='200' id='32' V200='8' input='true' structElemExists='true' V283='2' occurMinTimes='1' occurMaxTimes='1' minSize='-1' maxSize='-1' dataType='2' repHandlerStruct='' visible='true' inheritsFrom='' V281='13' V1='4' name='ZLSPR'>
      <mapNode t='190' idref='1'/>
    </child>
    <child t='200' id='33' V200='8' input='true' structElemExists='true' V283='2' occurMinTimes='1' occurMaxTimes='1' minSize='-1' maxSize='-1' dataType='2' repHandlerStruct='' visible='true' inheritsFrom='' V281='13' V1='4' name='FIPOS'>
      <mapNode t='190' idref='1'/>
    </child>
    <child t='200' id='34' V200='8' input='true' structElemExists='true' V283='2' occurMinTimes='1' occurMaxTimes='1' minSize='-1' maxSize='-1' dataType='2' repHandlerStruct='' visible='true' inheritsFrom='' V281='13' V1='4' name='ZLSCH'>
      <mapNode t='190' idref='1'/>
    </child>
  </inputMapElem>
  <outputMapElem t='200' id='35' V200='8' structElemExists='true' usedCount='7' V283='2' occurMaxTimes='1' minSize='-1' maxSize='-1' groupType='1' repHandlerStruct='' visible='true' inheritsFrom='' V281='13' modifiedFromParent_loop='true' V1='4' name='ZFIDCCP01' description='Complete FI document'>
    <mapNode t='190' idref='1'/>
    <loop>SimpleLoop([autoAdded="true"],in$/rootTag,{Filter},{Sort Keys},{Contexts})</loop>
    <child t='200' id='36' V200='8' structElemExists='true' usedCount='1' V283='2' occurMinTimes='1' occurMaxTimes='1' minSize='-1' maxSize='-1' inheritsFromCopyRule='28' groupType='1' repHandlerStruct='' visible='true' inheritsFrom='Structures/Jaggaer/Segments/EDI_DC40.xml' V281='13' V1='4' name='EDI_DC40' description='Control record'>
      <mapNode t='190' idref='1'/>
      <delimTerminator>\n</delimTerminator>
      <child t='200' id='37' V200='8' structElemExists='true' usedCount='1' V283='2' occurMinTimes='1' occurMaxTimes='1' minSize='10' maxSize='10' dataType='2' repHandlerStruct='' visible='true' inheritsFrom='' delimIncludeInitiator='true' V281='13' V1='4' name='TABNAM' description='Table Name'>
        <mapNode t='190' idref='1'/>
        <delimInitiator>EDI_DC40  </delimInitiator>
      </child>
      <child t='200' id='38' V200='8' structElemExists='true' usedCount='1' V283='2' occurMinTimes='1' occurMaxTimes='1' minSize='3' maxSize='3' dataType='2' repHandlerStruct='' visible='true' inheritsFrom='' V281='13' V1='4' name='MANDT' description='Client'>
        <mapNode t='190' idref='1'/>
      </child>
      <child t='200' id='39' V200='8' structElemExists='true' usedCount='1' V283='2' occurMinTimes='1' occurMaxTimes='1' minSize='16' maxSize='16' dataType='2' repHandlerStruct='' visible='true' inheritsFrom='' V281='13' V1='4' name='DOCNUM' description='Number'>
        <mapNode t='190' idref='1'/>
      </child>
      <child t='200' id='40' V200='8' structElemExists='true' usedCount='1' V283='2' occurMinTimes='1' occurMaxTimes='1' minSize='4' maxSize='4' dataType='2' repHandlerStruct='' visible='true' inheritsFrom='' V281='13' V1='4' name='DOCREL' description='SAP release'>
        <mapNode t='190' idref='1'/>
      </child>
      <child t='200' id='41' V200='8' structElemExists='true' usedCount='1' V283='2' occurMinTimes='1' occurMaxTimes='1' minSize='2' maxSize='2' dataType='2' repHandlerStruct='' visible='true' inheritsFrom='' V281='13' V1='4' name='STATUS' description='Status'>
        <mapNode t='190' idref='1'/>
      </child>
      <child t='200' id='42' V200='8' structElemExists='true' usedCount='1' V283='2' occurMinTimes='1' occurMaxTimes='1' minSize='1' maxSize='1' dataType='2' repHandlerStruct='' visible='true' inheritsFrom='' V281='13' V1='4' name='DIRECT' description='Direction'>
        <mapNode t='190' idref='1'/>
      </child>
      <child t='200' id='43' V200='8' structElemExists='true' usedCount='1' V283='2' occurMinTimes='1' occurMaxTimes='1' minSize='1' maxSize='1' dataType='2' repHandlerStruct='' visible='true' inheritsFrom='' V281='13' V1='4' name='OUTMOD' description='Output Mode'>
        <mapNode t='190' idref='1'/>
      </child>
      <child t='200' id='44' V200='8' structElemExists='true' usedCount='1' V283='2' occurMinTimes='1' occurMaxTimes='1' minSize='1' maxSize='1' dataType='2' repHandlerStruct='' visible='true' inheritsFrom='' V281='13' V1='4' name='EXPRSS' description='Express'>
        <mapNode t='190' idref='1'/>
      </child>
      <child t='200' id='45' V200='8' structElemExists='true' usedCount='1' V283='2' occurMinTimes='1' occurMaxTimes='1' minSize='1' maxSize='1' dataType='2' repHandlerStruct='' visible='true' inheritsFrom='' V281='13' V1='4' name='TEST' description='Test flag'>
        <mapNode t='190' idref='1'/>
      </child>
      <child t='200' id='46' V200='8' structElemExists='true' usedCount='1' V283='2' occurMinTimes='1' occurMaxTimes='1' minSize='30' maxSize='30' dataType='2' repHandlerStruct='' visible='true' inheritsFrom='' V281='13' V1='4' name='IDOCTYP' description='EDBAS Basic type'>
        <mapNode t='190' idref='1'/>
      </child>
      <child t='200' id='47' V200='8' structElemExists='true' usedCount='1' V283='2' occurMinTimes='1' occurMaxTimes='1' minSize='30' maxSize='30' dataType='2' repHandlerStruct='' visible='true' inheritsFrom='' V281='13' V1='4' name='CIMTYP' description='EDCIM Extension'>
        <mapNode t='190' idref='1'/>
      </child>
      <child t='200' id='48' V200='8' structElemExists='true' usedCount='1' V283='2' occurMinTimes='1' occurMaxTimes='1' minSize='30' maxSize='30' dataType='2' repHandlerStruct='' visible='true' inheritsFrom='' V281='13' V1='4' name='MESTYP' description='EDMSG Message type'>
        <mapNode t='190' idref='1'/>
      </child>
      <child t='200' id='49' V200='8' structElemExists='true' usedCount='1' V283='2' occurMinTimes='1' occurMaxTimes='1' minSize='3' maxSize='3' dataType='2' repHandlerStruct='' visible='true' inheritsFrom='' V281='13' V1='4' name='MESCOD' description='Message code'>
        <mapNode t='190' idref='1'/>
      </child>
      <child t='200' id='50' V200='8' structElemExists='true' usedCount='1' V283='2' occurMinTimes='1' occurMaxTimes='1' minSize='3' maxSize='3' dataType='2' repHandlerStruct='' visible='true' inheritsFrom='' V281='13' V1='4' name='MESFCT' description='Message Function'>
        <mapNode t='190' idref='1'/>
      </child>
      <child t='200' id='51' V200='8' structElemExists='true' usedCount='1' V283='2' occurMinTimes='1' occurMaxTimes='1' minSize='1' maxSize='1' dataType='2' repHandlerStruct='' visible='true' inheritsFrom='' V281='13' V1='4' name='STD' description='EDI Standard'>
        <mapNode t='190' idref='1'/>
      </child>
      <child t='200' id='52' V200='8' structElemExists='true' usedCount='1' V283='2' occurMinTimes='1' occurMaxTimes='1' minSize='6' maxSize='6' dataType='2' repHandlerStruct='' visible='true' inheritsFrom='' V281='13' V1='4' name='STDVRS' description='EDI std version'>
        <mapNode t='190' idref='1'/>
      </child>
      <child t='200' id='53' V200='8' structElemExists='true' usedCount='1' V283='2' occurMinTimes='1' occurMaxTimes='1' minSize='6' maxSize='6' dataType='2' repHandlerStruct='' visible='true' inheritsFrom='' V281='13' V1='4' name='STDMES' description='EDI message type'>
        <mapNode t='190' idref='1'/>
      </child>
      <child t='200' id='54' V200='8' structElemExists='true' usedCount='1' V283='2' occurMinTimes='1' occurMaxTimes='1' minSize='10' maxSize='10' dataType='2' repHandlerStruct='' visible='true' inheritsFrom='' V281='13' V1='4' name='SNDPOR' description='Sender port'>
        <mapNode t='190' idref='1'/>
      </child>
      <child t='200' id='55' V200='8' structElemExists='true' usedCount='1' V283='2' occurMinTimes='1' occurMaxTimes='1' minSize='2' maxSize='2' dataType='2' repHandlerStruct='' visible='true' inheritsFrom='' V281='13' V1='4' name='SNDPRT' description='Sender partner type'>
        <mapNode t='190' idref='1'/>
      </child>
      <child t='200' id='56' V200='8' structElemExists='true' usedCount='1' V283='2' occurMinTimes='1' occurMaxTimes='1' minSize='2' maxSize='2' dataType='2' repHandlerStruct='' visible='true' inheritsFrom='' V281='13' V1='4' name='SNDPFC' description='Sender function'>
        <mapNode t='190' idref='1'/>
      </child>
      <child t='200' id='57' V200='8' structElemExists='true' usedCount='1' V283='2' occurMinTimes='1' occurMaxTimes='1' minSize='10' maxSize='10' dataType='2' repHandlerStruct='' visible='true' inheritsFrom='' V281='13' V1='4' name='SNDPRN' description='Sender partner no.'>
        <mapNode t='190' idref='1'/>
      </child>
      <child t='200' id='58' V200='8' structElemExists='true' usedCount='1' V283='2' occurMinTimes='1' occurMaxTimes='1' minSize='21' maxSize='21' dataType='2' repHandlerStruct='' visible='true' inheritsFrom='' V281='13' V1='4' name='SNDSAD' description='SADR sender address'>
        <mapNode t='190' idref='1'/>
      </child>
      <child t='200' id='59' V200='8' structElemExists='true' usedCount='1' V283='2' occurMinTimes='1' occurMaxTimes='1' minSize='70' maxSize='70' dataType='2' repHandlerStruct='' visible='true' inheritsFrom='' V281='13' V1='4' name='SNDLAD'>
        <mapNode t='190' idref='1'/>
      </child>
      <child t='200' id='60' V200='8' structElemExists='true' usedCount='1' V283='2' occurMinTimes='1' occurMaxTimes='1' minSize='10' maxSize='10' dataType='2' repHandlerStruct='' visible='true' inheritsFrom='' V281='13' V1='4' name='RCVPOR' description='Receiver port'>
        <mapNode t='190' idref='1'/>
      </child>
      <child t='200' id='61' V200='8' structElemExists='true' usedCount='1' V283='2' occurMinTimes='1' occurMaxTimes='1' minSize='2' maxSize='2' dataType='2' repHandlerStruct='' visible='true' inheritsFrom='' V281='13' V1='4' name='RCVPRT' description='Receiver Partn. Type'>
        <mapNode t='190' idref='1'/>
      </child>
      <child t='200' id='62' V200='8' structElemExists='true' usedCount='1' V283='2' occurMinTimes='1' occurMaxTimes='1' minSize='2' maxSize='2' dataType='2' repHandlerStruct='' visible='true' inheritsFrom='' V281='13' V1='4' name='RCVPFC' description='Recipient partn. funct.'>
        <mapNode t='190' idref='1'/>
      </child>
      <child t='200' id='63' V200='8' structElemExists='true' usedCount='1' V283='2' occurMinTimes='1' occurMaxTimes='1' minSize='10' maxSize='10' dataType='2' repHandlerStruct='' visible='true' inheritsFrom='' V281='13' V1='4' name='RCVPRN' description='Receiv. Partner No.'>
        <mapNode t='190' idref='1'/>
      </child>
      <child t='200' id='64' V200='8' structElemExists='true' usedCount='1' V283='2' occurMinTimes='1' occurMaxTimes='1' minSize='21' maxSize='21' dataType='2' repHandlerStruct='' visible='true' inheritsFrom='' V281='13' V1='4' name='RCVSAD' description='SADR recipient addr.'>
        <mapNode t='190' idref='1'/>
      </child>
      <child t='200' id='65' V200='8' structElemExists='true' usedCount='1' V283='2' occurMinTimes='1' occurMaxTimes='1' minSize='70' maxSize='70' dataType='2' repHandlerStruct='' visible='true' inheritsFrom='' V281='13' V1='4' name='RCVLAD'>
        <mapNode t='190' idref='1'/>
      </child>
      <child t='200' id='66' V200='8' structElemExists='true' usedCount='1' V283='2' occurMinTimes='1' occurMaxTimes='1' minSize='8' maxSize='8' dataType='2' repHandlerStruct='' visible='true' inheritsFrom='' V281='13' V1='4' name='CREDAT' description='Created on'>
        <mapNode t='190' idref='1'/>
      </child>
      <child t='200' id='67' V200='8' structElemExists='true' usedCount='1' V283='2' occurMinTimes='1' occurMaxTimes='1' minSize='6' maxSize='6' dataType='2' repHandlerStruct='' visible='true' inheritsFrom='' V281='13' V1='4' name='CRETIM' description='Created at'>
        <mapNode t='190' idref='1'/>
      </child>
      <child t='200' id='68' V200='8' structElemExists='true' usedCount='1' V283='2' occurMinTimes='1' occurMaxTimes='1' minSize='14' maxSize='14' dataType='2' repHandlerStruct='' visible='true' inheritsFrom='' V281='13' V1='4' name='REFINT' description='Transmission'>
        <mapNode t='190' idref='1'/>
      </child>
      <child t='200' id='69' V200='8' structElemExists='true' usedCount='1' V283='2' occurMinTimes='1' occurMaxTimes='1' minSize='14' maxSize='14' dataType='2' repHandlerStruct='' visible='true' inheritsFrom='' V281='13' V1='4' name='REFGRP' description='Message Group'>
        <mapNode t='190' idref='1'/>
      </child>
      <child t='200' id='70' V200='8' structElemExists='true' usedCount='1' V283='2' occurMinTimes='1' occurMaxTimes='1' minSize='14' maxSize='14' dataType='2' repHandlerStruct='' visible='true' inheritsFrom='' V281='13' V1='4' name='REFMES' description='EDI message'>
        <mapNode t='190' idref='1'/>
      </child>
      <child t='200' id='71' V200='8' structElemExists='true' usedCount='1' V283='2' occurMinTimes='1' occurMaxTimes='1' minSize='70' maxSize='70' dataType='2' repHandlerStruct='' visible='true' inheritsFrom='' V281='13' V1='4' name='ARCKEY' description='Archive Key'>
        <mapNode t='190' idref='1'/>
      </child>
      <child t='200' id='72' V200='8' structElemExists='true' usedCount='1' V283='2' occurMinTimes='1' occurMaxTimes='1' minSize='20' maxSize='20' dataType='2' repHandlerStruct='' visible='true' inheritsFrom='' V281='13' V1='4' name='SERIAL' description='Serialization'>
        <mapNode t='190' idref='1'/>
      </child>
    </child>
    <child t='200' id='73' V200='8' structElemExists='true' usedCount='4' V283='2' occurMinTimes='1' occurMaxTimes='1' minSize='-1' maxSize='-1' inheritsFromCopyRule='28' groupType='1' repHandlerStruct='' visible='true' inheritsFrom='Structures/Jaggaer/Segments/ZE1FIKPF000.xml' V281='13' V1='4' name='ZE1FIKPF000' description='FI Document Header (BKPF)'>
      <mapNode t='190' idref='1'/>
      <delimTerminator>\n</delimTerminator>
      <child t='200' id='74' V200='8' structElemExists='true' usedCount='1' V283='2' occurMinTimes='1' occurMaxTimes='1' minSize='30' maxSize='30' dataType='2' repHandlerStruct='' visible='true' inheritsFrom='' delimIncludeInitiator='true' V281='13' V1='4' name='SEGNAM' description='Segment name'>
        <mapNode t='190' idref='1'/>
        <delimInitiator>ZE1FIKPF000                   </delimInitiator>
      </child>
      <child t='200' id='75' V200='8' structElemExists='true' usedCount='1' V283='2' occurMinTimes='1' occurMaxTimes='1' minSize='3' maxSize='3' dataType='2' repHandlerStruct='' visible='true' inheritsFrom='' V281='13' V1='4' name='MANDT' description='Client'>
        <mapNode t='190' idref='1'/>
      </child>
      <child t='200' id='76' V200='8' structElemExists='true' usedCount='1' V283='2' occurMinTimes='1' occurMaxTimes='1' minSize='16' maxSize='16' dataType='2' repHandlerStruct='' visible='true' inheritsFrom='' V281='13' V1='4' name='DOCNUM' description='Number'>
        <mapNode t='190' idref='1'/>
      </child>
      <child t='200' id='77' V200='8' structElemExists='true' usedCount='1' V283='2' occurMinTimes='1' occurMaxTimes='1' minSize='6' maxSize='6' dataType='2' repHandlerStruct='' visible='true' inheritsFrom='' V281='13' V1='4' name='SEGNUM' description='Record number'>
        <mapNode t='190' idref='1'/>
      </child>
      <child t='200' id='78' V200='8' structElemExists='true' usedCount='1' V283='2' occurMinTimes='1' occurMaxTimes='1' minSize='6' maxSize='6' dataType='2' repHandlerStruct='' visible='true' inheritsFrom='' V281='13' V1='4' name='PSGNUM' description='Parent record number'>
        <mapNode t='190' idref='1'/>
      </child>
      <child t='200' id='79' V200='8' structElemExists='true' usedCount='1' V283='2' occurMinTimes='1' occurMaxTimes='1' minSize='2' maxSize='2' dataType='2' repHandlerStruct='' visible='true' inheritsFrom='' V281='13' V1='4' name='HLEVEL' description='Hierarchy level'>
        <mapNode t='190' idref='1'/>
      </child>
      <child t='200' id='80' V200='8' structElemExists='true' usedCount='1' V283='2' occurMaxTimes='1' minSize='3' maxSize='3' dataType='2' repHandlerStruct='' visible='true' inheritsFrom='' V281='13' V1='4' name='TYPE' description='3-Byte field'>
        <mapNode t='190' idref='1'/>
      </child>
      <child t='200' id='81' V200='8' structElemExists='true' usedCount='4' V283='2' occurMaxTimes='1' minSize='2' maxSize='2' dataType='2' repHandlerStruct='' visible='true' inheritsFrom='' V281='13' modifiedFromParent_value='true' V1='4' name='BLART' description='Document type'>
        <mapNode t='190' idref='1'/>
        <value>in$/rootTag/BLART</value>
      </child>
      <child t='200' id='82' V200='8' structElemExists='true' usedCount='1' V283='2' occurMaxTimes='1' minSize='5' maxSize='5' dataType='2' repHandlerStruct='' visible='true' inheritsFrom='' V281='13' V1='4' name='WEARS' description='Currency Key'>
        <mapNode t='190' idref='1'/>
      </child>
      <child t='200' id='83' V200='8' structElemExists='true' usedCount='1' V283='2' occurMaxTimes='1' minSize='16' maxSize='16' dataType='2' repHandlerStruct='' visible='true' inheritsFrom='' V281='13' V1='4' name='XBLNR' description='Reference Document Number'>
        <mapNode t='190' idref='1'/>
      </child>
      <child t='200' id='84' V200='8' structElemExists='true' usedCount='1' V283='2' occurMaxTimes='1' minSize='25' maxSize='25' dataType='2' repHandlerStruct='' visible='true' inheritsFrom='' V281='13' V1='4' name='BKTXT' description='Document Header Text'>
        <mapNode t='190' idref='1'/>
      </child>
      <child t='200' id='85' V200='8' structElemExists='true' usedCount='1' V283='2' occurMaxTimes='1' minSize='4' maxSize='4' dataType='2' repHandlerStruct='' visible='true' inheritsFrom='' V281='13' V1='4' name='GLVOR' description='Business Transaction'>
        <mapNode t='190' idref='1'/>
      </child>
      <child t='200' id='86' V200='8' structElemExists='true' usedCount='1' V283='2' occurMaxTimes='1' minSize='25' maxSize='25' dataType='22' dataFormat='212' repHandlerStruct='' visible='true' inheritsFrom='' V281='13' V1='4' name='TOTAL_AMT' description='Amount in local currency'>
        <mapNode t='190' idref='1'/>
      </child>
      <child t='200' id='87' V200='8' structElemExists='true' usedCount='1' V283='2' occurMaxTimes='1' minSize='25' maxSize='25' dataType='22' dataFormat='212' repHandlerStruct='' visible='true' inheritsFrom='' V281='13' V1='4' name='AMT_WITHOUT_TAX' description='Amount in local currency'>
        <mapNode t='190' idref='1'/>
      </child>
      <child t='200' id='88' V200='8' structElemExists='true' usedCount='1' V283='2' occurMaxTimes='1' minSize='25' maxSize='25' dataType='22' dataFormat='212' repHandlerStruct='' visible='true' inheritsFrom='' V281='13' V1='4' name='TAX_AMT' description='Amount in local currency'>
        <mapNode t='190' idref='1'/>
      </child>
      <child t='200' id='89' V200='8' structElemExists='true' usedCount='1' V283='2' occurMaxTimes='1' minSize='50' maxSize='50' dataType='2' repHandlerStruct='' visible='true' inheritsFrom='' V281='13' V1='4' name='SGTXT' description='Item Text'>
        <mapNode t='190' idref='1'/>
      </child>
      <child t='200' id='90' V200='8' structElemExists='true' usedCount='1' V283='2' occurMaxTimes='1' minSize='18' maxSize='18' dataType='2' repHandlerStruct='' visible='true' inheritsFrom='' V281='13' V1='4' name='ZUONR' description='Assignment number'>
        <mapNode t='190' idref='1'/>
      </child>
      <child t='200' id='91' V200='8' structElemExists='true' usedCount='1' V283='2' occurMaxTimes='1' minSize='10' maxSize='10' dataType='2' repHandlerStruct='' visible='true' inheritsFrom='' V281='13' V1='4' name='LIFNR' description='Account Number of Vendor or Creditor'>
        <mapNode t='190' idref='1'/>
      </child>
      <child t='200' id='92' V200='8' structElemExists='true' usedCount='1' V283='2' occurMaxTimes='1' minSize='4' maxSize='4' dataType='2' repHandlerStruct='' visible='true' inheritsFrom='' V281='13' V1='4' name='VORGN' description='Transaction Type for General Ledger'>
        <mapNode t='190' idref='1'/>
      </child>
      <child t='200' id='93' V200='8' structElemExists='true' usedCount='1' V283='2' occurMaxTimes='1' minSize='14' maxSize='14' dataType='2' repHandlerStruct='' visible='true' inheritsFrom='' V281='13' V1='4' name='FIPOS' description='Commitment Item'>
        <mapNode t='190' idref='1'/>
      </child>
      <child t='200' id='94' V200='8' structElemExists='true' usedCount='1' V283='2' occurMaxTimes='1' minSize='12' maxSize='12' dataType='2' repHandlerStruct='' visible='true' inheritsFrom='' V281='13' V1='4' name='REF_01' description='Business Partner Reference Key'>
        <mapNode t='190' idref='1'/>
      </child>
      <child t='200' id='95' V200='8' structElemExists='true' usedCount='1' V283='2' occurMaxTimes='1' minSize='12' maxSize='12' dataType='2' repHandlerStruct='' visible='true' inheritsFrom='' V281='13' V1='4' name='REF_02' description='Business Partner Reference Key'>
        <mapNode t='190' idref='1'/>
      </child>
      <child t='200' id='96' V200='8' structElemExists='true' usedCount='1' V283='2' occurMaxTimes='1' minSize='20' maxSize='20' dataType='2' repHandlerStruct='' visible='true' inheritsFrom='' V281='13' V1='4' name='REF_03' description='Reference key for line item'>
        <mapNode t='190' idref='1'/>
      </child>
    </child>
    <child t='200' id='97' V200='8' structElemExists='true' usedCount='1' V283='2' occurMaxTimes='999999' minSize='-1' maxSize='-1' inheritsFromCopyRule='28' groupType='1' repHandlerStruct='' visible='true' inheritsFrom='Structures/Jaggaer/Segments/E2IDOCENHANCEMENT000.xml' V281='13' V1='4' name='E2IDOCENHANCEMENT000' description='Segment for Dynamic Enhancement of IDoc Types'>
      <mapNode t='190' idref='1'/>
      <delimTerminator>\n</delimTerminator>
      <child t='200' id='98' V200='8' structElemExists='true' usedCount='1' V283='2' occurMinTimes='1' occurMaxTimes='1' minSize='30' maxSize='30' dataType='2' repHandlerStruct='' visible='true' inheritsFrom='' delimIncludeInitiator='true' V281='13' V1='4' name='SEGNAM' description='Segment name'>
        <mapNode t='190' idref='1'/>
        <delimInitiator>E2IDOCENHANCEMENT000          </delimInitiator>
      </child>
      <child t='200' id='99' V200='8' structElemExists='true' usedCount='1' V283='2' occurMinTimes='1' occurMaxTimes='1' minSize='3' maxSize='3' dataType='2' repHandlerStruct='' visible='true' inheritsFrom='' V281='13' V1='4' name='MANDT' description='Client'>
        <mapNode t='190' idref='1'/>
      </child>
      <child t='200' id='100' V200='8' structElemExists='true' usedCount='1' V283='2' occurMinTimes='1' occurMaxTimes='1' minSize='16' maxSize='16' dataType='2' repHandlerStruct='' visible='true' inheritsFrom='' V281='13' V1='4' name='DOCNUM' description='Number'>
        <mapNode t='190' idref='1'/>
      </child>
      <child t='200' id='101' V200='8' structElemExists='true' usedCount='1' V283='2' occurMinTimes='1' occurMaxTimes='1' minSize='6' maxSize='6' dataType='2' repHandlerStruct='' visible='true' inheritsFrom='' V281='13' V1='4' name='SEGNUM' description='Record number'>
        <mapNode t='190' idref='1'/>
      </child>
      <child t='200' id='102' V200='8' structElemExists='true' usedCount='1' V283='2' occurMinTimes='1' occurMaxTimes='1' minSize='6' maxSize='6' dataType='2' repHandlerStruct='' visible='true' inheritsFrom='' V281='13' V1='4' name='PSGNUM' description='Parent record number'>
        <mapNode t='190' idref='1'/>
      </child>
      <child t='200' id='103' V200='8' structElemExists='true' usedCount='1' V283='2' occurMinTimes='1' occurMaxTimes='1' minSize='2' maxSize='2' dataType='2' repHandlerStruct='' visible='true' inheritsFrom='' V281='13' V1='4' name='HLEVEL' description='Hierarchy level'>
        <mapNode t='190' idref='1'/>
      </child>
      <child t='200' id='104' V200='8' structElemExists='true' usedCount='1' V283='2' occurMaxTimes='1' minSize='30' maxSize='30' dataType='2' repHandlerStruct='' visible='true' inheritsFrom='' V281='13' V1='4' name='IDENTIFIER' description='Data Containers for Enhancement of IDoc Types'>
        <mapNode t='190' idref='1'/>
      </child>
      <child t='200' id='105' V200='8' structElemExists='true' usedCount='1' V283='2' occurMaxTimes='1' minSize='970' maxSize='970' dataType='2' repHandlerStruct='' visible='true' inheritsFrom='' V281='13' V1='4' name='DATA' description='Data Container for IDoc Enhancement'>
        <mapNode t='190' idref='1'/>
      </child>
    </child>
  </outputMapElem>
  <inputRepRuntime t='692' id='428' V692='1' unnamedElemsNamespace='1' V690='1'>
    <namespaceContainers t='220' ref='Namespace Containers/Tender_Fee_Test_Idoc.xml'/>
  </inputRepRuntime>
  <outputRepRuntime t='704' id='106' V704='2' idoctyp='ZFIDCCP01' isTrimTrailingEmptyFields='true' V690='1' encoding='UTF-8'>
  </outputRepRuntime>
  <valueSets></valueSets>
  <inputXmlRepRuntime t='692' idref='428'/>
  <outputXmlRepRuntime t='692' id='107' V692='1' V690='1'>
  </outputXmlRepRuntime>
  <child t='165' id='2' V1='4' name='Document Bindings'>
    <child t='166' id='108' V166='5' docType='1' docReposPath='/TAL_INT_GIT/Sample Data/Tender_Fee_Test_Idoc/Tender_Fee_Test_Idoc' V1='4' name='in$/rootTag'>
      <elemNode t='200' idref='4'/>
    </child>
    <child t='166' id='109' V166='5' docType='2' V1='4' name='out$/ZFIDCCP01'>
      <elemNode t='200' idref='35'/>
    </child>
  </child>
  <child t='201' id='3' V1='4' name='Inherits From'>
  </child>
</root>
