<?xml version="1.0" encoding="UTF-8"?>
<root t='150' id='1' V150='13' creationTimestamp='0x17791fab9a7' V1='4' name='E2EDL37006' incarnation='104'>
  <rootElem t='167' id='2' V167='21' V283='2' occurMaxTimes='1' minSize='-1' maxSize='-1' groupType='1' repHandlerStruct='' visible='true' inheritsFrom='' V281='13' V1='4' name='E2EDL37006' description='Handling unit header'>
    <structNode t='150' idref='1'/>
    <delimTerminator>\n</delimTerminator>
    <child t='167' id='3' V167='21' V283='2' occurMinTimes='1' occurMaxTimes='1' minSize='30' maxSize='30' dataType='2' repHandlerStruct='' visible='true' inheritsFrom='' delimIncludeInitiator='true' V281='13' V1='4' name='SEGNAM' description='Segment name'>
      <structNode t='150' idref='1'/>
      <delimInitiator>E2EDL37006                    </delimInitiator>
    </child>
    <child t='167' id='4' V167='21' V283='2' occurMinTimes='1' occurMaxTimes='1' minSize='3' maxSize='3' dataType='2' repHandlerStruct='' visible='true' inheritsFrom='' V281='13' V1='4' name='MANDT' description='Client'>
      <structNode t='150' idref='1'/>
    </child>
    <child t='167' id='5' V167='21' V283='2' occurMinTimes='1' occurMaxTimes='1' minSize='16' maxSize='16' dataType='2' repHandlerStruct='' visible='true' inheritsFrom='' V281='13' V1='4' name='DOCNUM' description='Number'>
      <structNode t='150' idref='1'/>
    </child>
    <child t='167' id='6' V167='21' V283='2' occurMinTimes='1' occurMaxTimes='1' minSize='6' maxSize='6' dataType='2' repHandlerStruct='' visible='true' inheritsFrom='' V281='13' V1='4' name='SEGNUM' description='Record number'>
      <structNode t='150' idref='1'/>
    </child>
    <child t='167' id='7' V167='21' V283='2' occurMinTimes='1' occurMaxTimes='1' minSize='6' maxSize='6' dataType='2' repHandlerStruct='' visible='true' inheritsFrom='' V281='13' V1='4' name='PSGNUM' description='Parent record number'>
      <structNode t='150' idref='1'/>
    </child>
    <child t='167' id='8' V167='21' V283='2' occurMinTimes='1' occurMaxTimes='1' minSize='2' maxSize='2' dataType='2' repHandlerStruct='' visible='true' inheritsFrom='' V281='13' V1='4' name='HLEVEL' description='Hierarchy level'>
      <structNode t='150' idref='1'/>
    </child>
    <child t='167' id='9' V167='21' V283='2' occurMaxTimes='1' minSize='20' maxSize='20' dataType='2' repHandlerStruct='' visible='true' inheritsFrom='' V281='13' V1='4' name='EXIDV' description='External Handling Unit Identification'>
      <structNode t='150' idref='1'/>
    </child>
    <child t='167' id='10' V167='21' V283='2' occurMaxTimes='1' minSize='17' maxSize='17' dataType='22' dataFormat='212' repHandlerStruct='' visible='true' inheritsFrom='' V281='13' V1='4' name='TARAG' description='Tare Weight of Handling Unit'>
      <structNode t='150' idref='1'/>
    </child>
    <child t='167' id='11' V167='21' V283='2' occurMaxTimes='1' minSize='3' maxSize='3' dataType='2' repHandlerStruct='' visible='true' inheritsFrom='' V281='13' V1='4' name='GWEIT' description='Weight Unit Tare'>
      <structNode t='150' idref='1'/>
    </child>
    <child t='167' id='12' V167='21' V283='2' occurMaxTimes='1' minSize='17' maxSize='17' dataType='22' dataFormat='212' repHandlerStruct='' visible='true' inheritsFrom='' V281='13' V1='4' name='BRGEW' description='Total Weight of Handling Unit'>
      <structNode t='150' idref='1'/>
    </child>
    <child t='167' id='13' V167='21' V283='2' occurMaxTimes='1' minSize='17' maxSize='17' dataType='22' dataFormat='212' repHandlerStruct='' visible='true' inheritsFrom='' V281='13' V1='4' name='NTGEW' description='Loading Weight of Handling Unit'>
      <structNode t='150' idref='1'/>
    </child>
    <child t='167' id='14' V167='21' V283='2' occurMaxTimes='1' minSize='17' maxSize='17' dataType='22' dataFormat='212' repHandlerStruct='' visible='true' inheritsFrom='' V281='13' V1='4' name='MAGEW' description='Allowed Loading Weight of a Handling Unit'>
      <structNode t='150' idref='1'/>
    </child>
    <child t='167' id='15' V167='21' V283='2' occurMaxTimes='1' minSize='3' maxSize='3' dataType='2' repHandlerStruct='' visible='true' inheritsFrom='' V281='13' V1='4' name='GWEIM' description='Weight Unit'>
      <structNode t='150' idref='1'/>
    </child>
    <child t='167' id='16' V167='21' V283='2' occurMaxTimes='1' minSize='17' maxSize='17' dataType='22' dataFormat='212' repHandlerStruct='' visible='true' inheritsFrom='' V281='13' V1='4' name='BTVOL' description='Total Volume of Handling Unit'>
      <structNode t='150' idref='1'/>
    </child>
    <child t='167' id='17' V167='21' V283='2' occurMaxTimes='1' minSize='17' maxSize='17' dataType='22' dataFormat='212' repHandlerStruct='' visible='true' inheritsFrom='' V281='13' V1='4' name='NTVOL' description='Loading Volume of Handling Unit'>
      <structNode t='150' idref='1'/>
    </child>
    <child t='167' id='18' V167='21' V283='2' occurMaxTimes='1' minSize='17' maxSize='17' dataType='22' dataFormat='212' repHandlerStruct='' visible='true' inheritsFrom='' V281='13' V1='4' name='MAVOL' description='Allowed Loading Volume for Handling Unit'>
      <structNode t='150' idref='1'/>
    </child>
    <child t='167' id='19' V167='21' V283='2' occurMaxTimes='1' minSize='3' maxSize='3' dataType='2' repHandlerStruct='' visible='true' inheritsFrom='' V281='13' V1='4' name='VOLEM' description='Volume unit'>
      <structNode t='150' idref='1'/>
    </child>
    <child t='167' id='20' V167='21' V283='2' occurMaxTimes='1' minSize='17' maxSize='17' dataType='22' dataFormat='212' repHandlerStruct='' visible='true' inheritsFrom='' V281='13' V1='4' name='TAVOL' description='Tare Volume of Handling Unit'>
      <structNode t='150' idref='1'/>
    </child>
    <child t='167' id='21' V167='21' V283='2' occurMaxTimes='1' minSize='3' maxSize='3' dataType='2' repHandlerStruct='' visible='true' inheritsFrom='' V281='13' V1='4' name='VOLET' description='Volume Unit Tare'>
      <structNode t='150' idref='1'/>
    </child>
    <child t='167' id='22' V167='21' V283='2' occurMaxTimes='1' minSize='5' maxSize='5' dataType='2' repHandlerStruct='' visible='true' inheritsFrom='' V281='13' V1='4' name='VEGR2' description='Handling Unit Group 2                     (Freely Definable)'>
      <structNode t='150' idref='1'/>
    </child>
    <child t='167' id='23' V167='21' V283='2' occurMaxTimes='1' minSize='5' maxSize='5' dataType='2' repHandlerStruct='' visible='true' inheritsFrom='' V281='13' V1='4' name='VEGR1' description='Handling Unit Group 1                     (Freely Definable)'>
      <structNode t='150' idref='1'/>
    </child>
    <child t='167' id='24' V167='21' V283='2' occurMaxTimes='1' minSize='5' maxSize='5' dataType='2' repHandlerStruct='' visible='true' inheritsFrom='' V281='13' V1='4' name='VEGR3' description='Handling Unit Group 3                     (Freely Definable)'>
      <structNode t='150' idref='1'/>
    </child>
    <child t='167' id='25' V167='21' V283='2' occurMaxTimes='1' minSize='18' maxSize='18' dataType='2' repHandlerStruct='' visible='true' inheritsFrom='' V281='13' V1='4' name='VHILM' description='Packaging Materials'>
      <structNode t='150' idref='1'/>
    </child>
    <child t='167' id='26' V167='21' V283='2' occurMaxTimes='1' minSize='5' maxSize='5' dataType='2' repHandlerStruct='' visible='true' inheritsFrom='' V281='13' V1='4' name='VEGR4' description='Handling Unit Group 4                     (Freely Definable)'>
      <structNode t='150' idref='1'/>
    </child>
    <child t='167' id='27' V167='21' V283='2' occurMaxTimes='1' minSize='15' maxSize='15' dataType='22' dataFormat='212' repHandlerStruct='' visible='true' inheritsFrom='' V281='13' V1='4' name='LAENG' description='Length'>
      <structNode t='150' idref='1'/>
    </child>
    <child t='167' id='28' V167='21' V283='2' occurMaxTimes='1' minSize='5' maxSize='5' dataType='2' repHandlerStruct='' visible='true' inheritsFrom='' V281='13' V1='4' name='VEGR5' description='Handling Unit Group 5                     (Freely Definable)'>
      <structNode t='150' idref='1'/>
    </child>
    <child t='167' id='29' V167='21' V283='2' occurMaxTimes='1' minSize='15' maxSize='15' dataType='22' dataFormat='212' repHandlerStruct='' visible='true' inheritsFrom='' V281='13' V1='4' name='BREIT' description='Width'>
      <structNode t='150' idref='1'/>
    </child>
    <child t='167' id='30' V167='21' V283='2' occurMaxTimes='1' minSize='15' maxSize='15' dataType='22' dataFormat='212' repHandlerStruct='' visible='true' inheritsFrom='' V281='13' V1='4' name='HOEHE' description='Height'>
      <structNode t='150' idref='1'/>
    </child>
    <child t='167' id='31' V167='21' V283='2' occurMaxTimes='1' minSize='3' maxSize='3' dataType='2' repHandlerStruct='' visible='true' inheritsFrom='' V281='13' V1='4' name='MEABM' description='Unit of Dimension for Length/Width/Height'>
      <structNode t='150' idref='1'/>
    </child>
    <child t='167' id='32' V167='21' V283='2' occurMaxTimes='1' minSize='40' maxSize='40' dataType='2' repHandlerStruct='' visible='true' inheritsFrom='' V281='13' V1='4' name='INHALT' description='Description of Handling Unit Content'>
      <structNode t='150' idref='1'/>
    </child>
    <child t='167' id='33' V167='21' V283='2' occurMaxTimes='1' minSize='4' maxSize='4' dataType='2' repHandlerStruct='' visible='true' inheritsFrom='' V281='13' V1='4' name='VHART' description='Packaging Material Type'>
      <structNode t='150' idref='1'/>
    </child>
    <child t='167' id='34' V167='21' V283='2' occurMaxTimes='1' minSize='4' maxSize='4' dataType='2' repHandlerStruct='' visible='true' inheritsFrom='' V281='13' V1='4' name='MAGRV' description='Material Group: Packaging Materials'>
      <structNode t='150' idref='1'/>
    </child>
    <child t='167' id='35' V167='21' V283='2' occurMaxTimes='1' minSize='8' maxSize='8' dataType='22' dataFormat='212' repHandlerStruct='' visible='true' inheritsFrom='' V281='13' V1='4' name='LADLG' description='Lgth of loading platform in lgth of LdPlat measurement units'>
      <structNode t='150' idref='1'/>
    </child>
    <child t='167' id='36' V167='21' V283='2' occurMaxTimes='1' minSize='3' maxSize='3' dataType='2' repHandlerStruct='' visible='true' inheritsFrom='' V281='13' V1='4' name='LADEH' description='Unit of measure to measure the length of loading platform'>
      <structNode t='150' idref='1'/>
    </child>
    <child t='167' id='37' V167='21' V283='2' occurMaxTimes='1' minSize='4' maxSize='4' dataType='22' dataFormat='212' repHandlerStruct='' visible='true' inheritsFrom='' V281='13' V1='4' name='FARZT' description='Travel Time'>
      <structNode t='150' idref='1'/>
    </child>
    <child t='167' id='38' V167='21' V283='2' occurMaxTimes='1' minSize='3' maxSize='3' dataType='2' repHandlerStruct='' visible='true' inheritsFrom='' V281='13' V1='4' name='FAREH' description='Unit of travel time'>
      <structNode t='150' idref='1'/>
    </child>
    <child t='167' id='39' V167='21' V283='2' occurMaxTimes='1' minSize='8' maxSize='8' dataType='22' dataFormat='212' repHandlerStruct='' visible='true' inheritsFrom='' V281='13' V1='4' name='ENTFE' description='Distance Travelled'>
      <structNode t='150' idref='1'/>
    </child>
    <child t='167' id='40' V167='21' V283='2' occurMaxTimes='1' minSize='3' maxSize='3' dataType='2' repHandlerStruct='' visible='true' inheritsFrom='' V281='13' V1='4' name='EHENT' description='Unit of distance'>
      <structNode t='150' idref='1'/>
    </child>
    <child t='167' id='41' V167='21' V283='2' occurMaxTimes='1' minSize='1' maxSize='1' dataType='2' repHandlerStruct='' visible='true' inheritsFrom='' V281='13' V1='4' name='VELTP' description='Packaging Material Category'>
      <structNode t='150' idref='1'/>
      <child t='167' id='42' V167='21' V283='2' occurMaxTimes='1' minSize='-1' maxSize='-1' dataType='2' elemType='5' repHandlerStruct='' visible='true' inheritsFrom='' V281='13' V1='4' name='A' description='Means of transport'>
        <structNode t='150' idref='1'/>
      </child>
      <child t='167' id='43' V167='21' V283='2' occurMaxTimes='1' minSize='-1' maxSize='-1' dataType='2' elemType='5' repHandlerStruct='' visible='true' inheritsFrom='' V281='13' V1='4' name='B' description='Transport equipment'>
        <structNode t='150' idref='1'/>
      </child>
      <child t='167' id='44' V167='21' V283='2' occurMaxTimes='1' minSize='-1' maxSize='-1' dataType='2' elemType='5' repHandlerStruct='' visible='true' inheritsFrom='' V281='13' V1='4' name='C' description='Packaging materials'>
        <structNode t='150' idref='1'/>
      </child>
      <child t='167' id='45' V167='21' V283='2' occurMaxTimes='1' minSize='-1' maxSize='-1' dataType='2' elemType='5' repHandlerStruct='' visible='true' inheritsFrom='' V281='13' V1='4' name='D' description='Auxiliary packaging material'>
        <structNode t='150' idref='1'/>
      </child>
    </child>
    <child t='167' id='46' V167='21' V283='2' occurMaxTimes='1' minSize='20' maxSize='20' dataType='2' repHandlerStruct='' visible='true' inheritsFrom='' V281='13' V1='4' name='EXIDV2' description='Handling Unit&apos;s 2nd External Identification'>
      <structNode t='150' idref='1'/>
    </child>
    <child t='167' id='47' V167='21' V283='2' occurMaxTimes='1' minSize='3' maxSize='3' dataType='2' repHandlerStruct='' visible='true' inheritsFrom='' V281='13' V1='4' name='LANDT' description='Country providing means of transport'>
      <structNode t='150' idref='1'/>
    </child>
    <child t='167' id='48' V167='21' V283='2' occurMaxTimes='1' minSize='3' maxSize='3' dataType='2' repHandlerStruct='' visible='true' inheritsFrom='' V281='13' V1='4' name='LANDF' description='Driver&apos;s Nationality'>
      <structNode t='150' idref='1'/>
    </child>
    <child t='167' id='49' V167='21' V283='2' occurMaxTimes='1' minSize='35' maxSize='35' dataType='2' repHandlerStruct='' visible='true' inheritsFrom='' V281='13' V1='4' name='NAMEF' description='Driver name'>
      <structNode t='150' idref='1'/>
    </child>
    <child t='167' id='50' V167='21' V283='2' occurMaxTimes='1' minSize='35' maxSize='35' dataType='2' repHandlerStruct='' visible='true' inheritsFrom='' V281='13' V1='4' name='NAMBE' description='Alternate Driver&apos;s Name'>
      <structNode t='150' idref='1'/>
    </child>
    <child t='167' id='51' V167='21' V283='2' occurMaxTimes='1' minSize='22' maxSize='22' dataType='2' repHandlerStruct='' visible='true' inheritsFrom='' V281='13' V1='4' name='VHILM_KU' description='Material belonging to the customer'>
      <structNode t='150' idref='1'/>
    </child>
    <child t='167' id='52' V167='21' V283='2' occurMaxTimes='1' minSize='40' maxSize='40' dataType='2' repHandlerStruct='' visible='true' inheritsFrom='' V281='13' V1='4' name='VEBEZ' description='Description of Packaging Material'>
      <structNode t='150' idref='1'/>
    </child>
    <child t='167' id='53' V167='21' V283='2' occurMaxTimes='1' minSize='1' maxSize='1' dataType='2' repHandlerStruct='' visible='true' inheritsFrom='' V281='13' V1='4' name='SMGKN' description='SMG identification for material tag'>
      <structNode t='150' idref='1'/>
      <child t='167' id='54' V167='21' V283='2' occurMaxTimes='1' minSize='-1' maxSize='-1' dataType='2' elemType='5' repHandlerStruct='' visible='true' inheritsFrom='' V281='13' V1='4' name='S' description='Single label'>
        <structNode t='150' idref='1'/>
      </child>
      <child t='167' id='55' V167='21' V283='2' occurMaxTimes='1' minSize='-1' maxSize='-1' dataType='2' elemType='5' repHandlerStruct='' visible='true' inheritsFrom='' V281='13' V1='4' name='M' description='Main label'>
        <structNode t='150' idref='1'/>
      </child>
      <child t='167' id='56' V167='21' V283='2' occurMaxTimes='1' minSize='-1' maxSize='-1' dataType='2' elemType='5' repHandlerStruct='' visible='true' inheritsFrom='' V281='13' V1='4' name='G' description='Group label'>
        <structNode t='150' idref='1'/>
      </child>
    </child>
    <child t='167' id='57' V167='21' V283='2' occurMaxTimes='1' minSize='35' maxSize='35' dataType='2' repHandlerStruct='' visible='true' inheritsFrom='' V281='13' V1='4' name='KDMAT35' description='Partner&apos;s (Customer&apos;s or Vendor&apos;s) Packaging Material'>
      <structNode t='150' idref='1'/>
    </child>
    <child t='167' id='58' V167='21' V283='2' occurMaxTimes='1' minSize='10' maxSize='10' dataType='2' repHandlerStruct='' visible='true' inheritsFrom='' V281='13' V1='4' name='SORTL' description='Sort field'>
      <structNode t='150' idref='1'/>
    </child>
    <child t='167' id='59' V167='21' V283='2' occurMaxTimes='1' minSize='12' maxSize='12' dataType='2' repHandlerStruct='' visible='true' inheritsFrom='' V281='13' V1='4' name='ERNAM' description='Name of Person who Created the Object'>
      <structNode t='150' idref='1'/>
    </child>
    <child t='167' id='60' V167='21' V283='2' occurMaxTimes='1' minSize='1' maxSize='1' dataType='2' repHandlerStruct='' visible='true' inheritsFrom='' V281='13' V1='4' name='GEWFX' description='Weight and Volume Fixed'>
      <structNode t='150' idref='1'/>
      <child t='167' id='61' V167='21' V283='2' occurMaxTimes='1' minSize='-1' maxSize='-1' dataType='2' elemType='5' repHandlerStruct='' visible='true' inheritsFrom='' V281='13' V1='4' name='X' description='Yes'>
        <structNode t='150' idref='1'/>
      </child>
    </child>
    <child t='167' id='62' V167='21' V283='2' occurMaxTimes='1' minSize='1' maxSize='1' dataType='2' repHandlerStruct='' visible='true' inheritsFrom='' V281='13' V1='4' name='ERLKZ' description='Status (at this time without functionality)'>
      <structNode t='150' idref='1'/>
      <child t='167' id='63' V167='21' V283='2' occurMaxTimes='1' minSize='-1' maxSize='-1' dataType='2' elemType='5' repHandlerStruct='' visible='true' inheritsFrom='' V281='13' V1='4' name='X' description='Yes'>
        <structNode t='150' idref='1'/>
      </child>
    </child>
    <child t='167' id='64' V167='21' V283='2' occurMaxTimes='1' minSize='1' maxSize='1' dataType='2' repHandlerStruct='' visible='true' inheritsFrom='' V281='13' V1='4' name='EXIDA' description='Type of External Handling Unit Identifier' checksumValid='true' checksum='xDqQLZDmNG859XNT+bGP5PcuZwg='>
      <structNode t='150' idref='1'/>
      <child t='167' id='65' V167='21' V283='2' occurMaxTimes='1' minSize='-1' maxSize='-1' dataType='2' elemType='5' repHandlerStruct='' visible='true' inheritsFrom='' V281='13' V1='4' name='A' description='External HU identification = VEKP-VENUM (no HU management)'>
        <structNode t='150' idref='1'/>
      </child>
      <child t='167' id='66' V167='21' V283='2' occurMaxTimes='1' minSize='-1' maxSize='-1' dataType='2' elemType='5' repHandlerStruct='' visible='true' inheritsFrom='' V281='13' V1='4' name='B' description='Number assigned by customer (no HU management)'>
        <structNode t='150' idref='1'/>
      </child>
      <child t='167' id='67' V167='21' V283='2' occurMaxTimes='1' minSize='-1' maxSize='-1' dataType='2' elemType='5' repHandlerStruct='' visible='true' inheritsFrom='' V281='13' V1='4' name='C' description='SSCC18 internal'>
        <structNode t='150' idref='1'/>
      </child>
      <child t='167' id='68' V167='21' V283='2' occurMaxTimes='1' minSize='-1' maxSize='-1' dataType='2' elemType='5' repHandlerStruct='' visible='true' inheritsFrom='' V281='13' V1='4' name='D' description='SSCC18 external'>
        <structNode t='150' idref='1'/>
      </child>
      <child t='167' id='69' V167='21' V283='2' occurMaxTimes='1' minSize='-1' maxSize='-1' dataType='2' elemType='5' repHandlerStruct='' visible='true' inheritsFrom='' V281='13' V1='4' name='E' description='No. rnge obj. HU_VEKP internal interval - SSCC18 before GI'>
        <structNode t='150' idref='1'/>
      </child>
      <child t='167' id='70' V167='21' V283='2' occurMaxTimes='1' minSize='-1' maxSize='-1' dataType='2' elemType='5' repHandlerStruct='' visible='true' inheritsFrom='' V281='13' V1='4' name='F' description='No. rnge obj. HU_VEKP external interval - SSCC18 before GI'>
        <structNode t='150' idref='1'/>
      </child>
      <child t='167' id='71' V167='21' V283='2' occurMaxTimes='1' minSize='-1' maxSize='-1' dataType='2' elemType='5' repHandlerStruct='' visible='true' inheritsFrom='' V281='13' V1='4' name='G' description='$ number for packing proposal - only for object &apos;02&apos;'>
        <structNode t='150' idref='1'/>
      </child>
      <child t='167' id='72' V167='21' V283='2' occurMaxTimes='1' minSize='-1' maxSize='-1' dataType='2' elemType='5' repHandlerStruct='' visible='true' inheritsFrom='' V281='13' V1='4' name='H' description='SSCC18 from vendor'>
        <structNode t='150' idref='1'/>
      </child>
    </child>
    <child t='167' id='73' V167='21' V283='2' occurMaxTimes='1' minSize='4' maxSize='4' dataType='2' repHandlerStruct='' visible='true' inheritsFrom='' V281='13' V1='4' name='MOVE_STATUS' description='Handling unit status' checksumValid='true' checksum='fxnZi+4rdPlgodjEjrnoexrQ3Go='>
      <structNode t='150' idref='1'/>
      <child t='167' id='74' V167='21' V283='2' occurMaxTimes='1' minSize='-1' maxSize='-1' dataType='2' elemType='5' repHandlerStruct='' visible='true' inheritsFrom='' V281='13' V1='4' name='0001' description='Planned'>
        <structNode t='150' idref='1'/>
      </child>
      <child t='167' id='75' V167='21' V283='2' occurMaxTimes='1' minSize='-1' maxSize='-1' dataType='2' elemType='5' repHandlerStruct='' visible='true' inheritsFrom='' V281='13' V1='4' name='0010' description='Implemented - stock not posted as goods receipt'>
        <structNode t='150' idref='1'/>
      </child>
      <child t='167' id='76' V167='21' V283='2' occurMaxTimes='1' minSize='-1' maxSize='-1' dataType='2' elemType='5' repHandlerStruct='' visible='true' inheritsFrom='' V281='13' V1='4' name='0020' description='Stock at a non-HU storage location'>
        <structNode t='150' idref='1'/>
      </child>
      <child t='167' id='77' V167='21' V283='2' occurMaxTimes='1' minSize='-1' maxSize='-1' dataType='2' elemType='5' repHandlerStruct='' visible='true' inheritsFrom='' V281='13' V1='4' name='0030' description='Stock at HU storage location'>
        <structNode t='150' idref='1'/>
      </child>
      <child t='167' id='78' V167='21' V283='2' occurMaxTimes='1' minSize='-1' maxSize='-1' dataType='2' elemType='5' repHandlerStruct='' visible='true' inheritsFrom='' V281='13' V1='4' name='0031' description='Physical inventory'>
        <structNode t='150' idref='1'/>
      </child>
      <child t='167' id='79' V167='21' V283='2' occurMaxTimes='1' minSize='-1' maxSize='-1' dataType='2' elemType='5' repHandlerStruct='' visible='true' inheritsFrom='' V281='13' V1='4' name='0040' description='In transit'>
        <structNode t='150' idref='1'/>
      </child>
      <child t='167' id='80' V167='21' V283='2' occurMaxTimes='1' minSize='-1' maxSize='-1' dataType='2' elemType='5' repHandlerStruct='' visible='true' inheritsFrom='' V281='13' V1='4' name='0050' description='Posted for GI'>
        <structNode t='150' idref='1'/>
      </child>
      <child t='167' id='81' V167='21' V283='2' occurMaxTimes='1' minSize='-1' maxSize='-1' dataType='2' elemType='5' repHandlerStruct='' visible='true' inheritsFrom='' V281='13' V1='4' name='0060' description='Deleted'>
        <structNode t='150' idref='1'/>
      </child>
      <child t='167' id='82' V167='21' V283='2' occurMaxTimes='1' minSize='-1' maxSize='-1' dataType='2' elemType='5' repHandlerStruct='' visible='true' inheritsFrom='' V281='13' V1='4' name='0015' description='Visually Checked'>
        <structNode t='150' idref='1'/>
      </child>
    </child>
    <child t='167' id='83' V167='21' V283='2' occurMaxTimes='1' minSize='22' maxSize='22' dataType='2' repHandlerStruct='' visible='true' inheritsFrom='' V281='13' V1='4' name='PACKVORSCHR' description='Text string 22 characters'>
      <structNode t='150' idref='1'/>
    </child>
    <child t='167' id='84' V167='21' V283='2' occurMaxTimes='1' minSize='1' maxSize='1' dataType='2' repHandlerStruct='' visible='true' inheritsFrom='' V281='13' V1='4' name='PACKVORSCHR_ST' description='Single-Character Flag'>
      <structNode t='150' idref='1'/>
    </child>
    <child t='167' id='85' V167='21' V283='2' occurMaxTimes='1' minSize='1' maxSize='1' dataType='2' repHandlerStruct='' visible='true' inheritsFrom='' V281='13' V1='4' name='LABELTYP' description='Checkbox: Do Not Print External Shipping Label'>
      <structNode t='150' idref='1'/>
      <child t='167' id='86' V167='21' V283='2' occurMaxTimes='1' minSize='-1' maxSize='-1' dataType='2' elemType='5' repHandlerStruct='' visible='true' inheritsFrom='' V281='13' V1='4' name='X' description='Yes'>
        <structNode t='150' idref='1'/>
      </child>
    </child>
    <child t='167' id='87' V167='21' V283='2' occurMaxTimes='1' minSize='17' maxSize='17' dataType='2' repHandlerStruct='' visible='true' inheritsFrom='' V281='13' V1='4' name='ZUL_AUFL' description='17-Char. Field'>
      <structNode t='150' idref='1'/>
    </child>
    <child t='167' id='88' V167='21' V283='2' occurMaxTimes='1' minSize='40' maxSize='40' dataType='2' repHandlerStruct='' visible='true' inheritsFrom='' V281='13' V1='4' name='VHILM_EXTERNAL' description='Shipping Material'>
      <structNode t='150' idref='1'/>
    </child>
    <child t='167' id='89' V167='21' V283='2' occurMaxTimes='1' minSize='10' maxSize='10' dataType='2' repHandlerStruct='' visible='true' inheritsFrom='' V281='13' V1='4' name='VHILM_VERSION' description='Version Number for Field VHILM'>
      <structNode t='150' idref='1'/>
    </child>
    <child t='167' id='90' V167='21' V283='2' occurMaxTimes='1' minSize='32' maxSize='32' dataType='2' repHandlerStruct='' visible='true' inheritsFrom='' V281='13' V1='4' name='VHILM_GUID' description='External GUID for Field VHILM'>
      <structNode t='150' idref='1'/>
    </child>
    <child t='167' id='91' V167='21' V283='2' occurMaxTimes='1' minSize='40' maxSize='40' dataType='2' repHandlerStruct='' visible='true' inheritsFrom='' V281='13' V1='4' name='KDMAT35_EXTERNAL' description='Long Material Number (Future Development) for KDMAT Field'>
      <structNode t='150' idref='1'/>
    </child>
    <child t='167' id='92' V167='21' V283='2' occurMaxTimes='1' minSize='10' maxSize='10' dataType='2' repHandlerStruct='' visible='true' inheritsFrom='' V281='13' V1='4' name='KDMAT35_VERSION' description='Version Number (Future Development) for KDMAT35 Field'>
      <structNode t='150' idref='1'/>
    </child>
    <child t='167' id='93' V167='21' V283='2' occurMaxTimes='1' minSize='32' maxSize='32' dataType='2' repHandlerStruct='' visible='true' inheritsFrom='' V281='13' V1='4' name='KDMAT35_GUID' description='External GUID (Future Development) for KDMAT35 Field'>
      <structNode t='150' idref='1'/>
    </child>
    <child t='167' id='94' V167='21' V283='2' occurMaxTimes='1' minSize='40' maxSize='40' dataType='2' repHandlerStruct='' visible='true' inheritsFrom='' V281='13' V1='4' name='VHILM_KU_EXTERNAL' description='Long Material Number (Future Development) for Field VHILM'>
      <structNode t='150' idref='1'/>
    </child>
    <child t='167' id='95' V167='21' V283='2' occurMaxTimes='1' minSize='10' maxSize='10' dataType='2' repHandlerStruct='' visible='true' inheritsFrom='' V281='13' V1='4' name='VHILM_KU_VERSION' description='Version Number (Future Development) for Field VHILM_KU'>
      <structNode t='150' idref='1'/>
    </child>
    <child t='167' id='96' V167='21' V283='2' occurMaxTimes='1' minSize='32' maxSize='32' dataType='2' repHandlerStruct='' visible='true' inheritsFrom='' V281='13' V1='4' name='VHILM_KU_GUID' description='External GUID (Future Development) for Field VHILM_KU'>
      <structNode t='150' idref='1'/>
    </child>
    <child t='167' id='97' V167='21' V283='2' occurMaxTimes='1' minSize='40' maxSize='40' dataType='2' repHandlerStruct='' visible='true' inheritsFrom='' V281='13' V1='4' name='VHILM_LONG' description='Packaging Materials'>
      <structNode t='150' idref='1'/>
    </child>
  </rootElem>
  <defaultRep t='181' id='98' V181='2' V170='10' V704='2' isTrimTrailingEmptyFields='true' V690='1' encoding='UTF-8' ignoreExcluded='true' fixInvalidCharacters='true' V1='4' name='IDocs'>
  </defaultRep>
  <child t='162' id='99' V1='4' name='Representations'>
    <child t='181' idref='98'/>
    <child t='172' id='100' V172='6' autoFixNamespaceMismatch='true' V170='10' V692='1' V690='1' ignoreExcluded='true' fixInvalidCharacters='true' V1='4' name='XML'>
    </child>
  </child>
  <child t='165' id='101' V1='4' name='Document Bindings'>
  </child>
</root>
